{"nodes": [{"id": "c_users_praja_onedrive_desktop_test_env_repositories_kairo_phantom_phantom_core_src_cua_cua_executor_rs", "label": "cua_executor.rs", "file_type": "code", "source_file": "C:\\Users\\praja\\OneDrive\\Desktop\\test-env\\repositories\\kairo-phantom\\phantom-core\\src\\cua\\cua_executor.rs", "source_location": "L1"}, {"id": "cua_cua_executor_executorerror", "label": "ExecutorError", "file_type": "code", "source_file": "C:\\Users\\praja\\OneDrive\\Desktop\\test-env\\repositories\\kairo-phantom\\phantom-core\\src\\cua\\cua_executor.rs", "source_location": "L14"}, {"id": "display", "label": "Display", "file_type": "code", "source_file": "C:\\Users\\praja\\OneDrive\\Desktop\\test-env\\repositories\\kairo-phantom\\phantom-core\\src\\cua\\cua_executor.rs", "source_location": "L22"}, {"id": "cua_cua_executor_executorerror_fmt", "label": ".fmt()", "file_type": "code", "source_file": "C:\\Users\\praja\\OneDrive\\Desktop\\test-env\\repositories\\kairo-phantom\\phantom-core\\src\\cua\\cua_executor.rs", "source_location": "L23"}, {"id": "formatter", "label": "Formatter", "file_type": "code", "source_file": "C:\\Users\\praja\\OneDrive\\Desktop\\test-env\\repositories\\kairo-phantom\\phantom-core\\src\\cua\\cua_executor.rs", "source_location": "L23"}, {"id": "result", "label": "Result", "file_type": "code", "source_file": "C:\\Users\\praja\\OneDrive\\Desktop\\test-env\\repositories\\kairo-phantom\\phantom-core\\src\\cua\\cua_executor.rs", "source_location": "L23"}, {"id": "cua_cua_executor_execute", "label": "execute()", "file_type": "code", "source_file": "C:\\Users\\praja\\OneDrive\\Desktop\\test-env\\repositories\\kairo-phantom\\phantom-core\\src\\cua\\cua_executor.rs", "source_location": "L39"}, {"id": "cuaaction", "label": "CuaAction", "file_type": "code", "source_file": "C:\\Users\\praja\\OneDrive\\Desktop\\test-env\\repositories\\kairo-phantom\\phantom-core\\src\\cua\\cua_executor.rs", "source_location": "L39"}, {"id": "cuacontext", "label": "CuaContext", "file_type": "code", "source_file": "C:\\Users\\praja\\OneDrive\\Desktop\\test-env\\repositories\\kairo-phantom\\phantom-core\\src\\cua\\cua_executor.rs", "source_location": "L39"}, {"id": "cuabackend", "label": "CuaBackend", "file_type": "code", "source_file": "C:\\Users\\praja\\OneDrive\\Desktop\\test-env\\repositories\\kairo-phantom\\phantom-core\\src\\cua\\cua_executor.rs", "source_location": "L39"}, {"id": "cancellationtoken", "label": "CancellationToken", "file_type": "code", "source_file": "C:\\Users\\praja\\OneDrive\\Desktop\\test-env\\repositories\\kairo-phantom\\phantom-core\\src\\cua\\cua_executor.rs", "source_location": "L39"}, {"id": "cuaresult", "label": "CuaResult", "file_type": "code", "source_file": "C:\\Users\\praja\\OneDrive\\Desktop\\test-env\\repositories\\kairo-phantom\\phantom-core\\src\\cua\\cua_executor.rs", "source_location": "L39"}, {"id": "cua_cua_executor_execute_enigo", "label": "execute_enigo()", "file_type": "code", "source_file": "C:\\Users\\praja\\OneDrive\\Desktop\\test-env\\repositories\\kairo-phantom\\phantom-core\\src\\cua\\cua_executor.rs", "source_location": "L140"}, {"id": "cua_cua_executor_execute_well_known_shortcut", "label": "execute_well_known_shortcut()", "file_type": "code", "source_file": "C:\\Users\\praja\\OneDrive\\Desktop\\test-env\\repositories\\kairo-phantom\\phantom-core\\src\\cua\\cua_executor.rs", "source_location": "L285"}, {"id": "enigo", "label": "Enigo", "file_type": "code", "source_file": "C:\\Users\\praja\\OneDrive\\Desktop\\test-env\\repositories\\kairo-phantom\\phantom-core\\src\\cua\\cua_executor.rs", "source_location": "L285"}, {"id": "wellknownshortcut", "label": "WellKnownShortcut", "file_type": "code", "source_file": "C:\\Users\\praja\\OneDrive\\Desktop\\test-env\\repositories\\kairo-phantom\\phantom-core\\src\\cua\\cua_executor.rs", "source_location": "L285"}, {"id": "string", "label": "String", "file_type": "code", "source_file": "C:\\Users\\praja\\OneDrive\\Desktop\\test-env\\repositories\\kairo-phantom\\phantom-core\\src\\cua\\cua_executor.rs", "source_location": "L285"}, {"id": "cua_cua_executor_execute_cua_driver", "label": "execute_cua_driver()", "file_type": "code", "source_file": "C:\\Users\\praja\\OneDrive\\Desktop\\test-env\\repositories\\kairo-phantom\\phantom-core\\src\\cua\\cua_executor.rs", "source_location": "L327"}, {"id": "cua_cua_executor_find_cua_driver", "label": "find_cua_driver()", "file_type": "code", "source_file": "C:\\Users\\praja\\OneDrive\\Desktop\\test-env\\repositories\\kairo-phantom\\phantom-core\\src\\cua\\cua_executor.rs", "source_location": "L368"}, {"id": "option", "label": "Option", "file_type": "code", "source_file": "C:\\Users\\praja\\OneDrive\\Desktop\\test-env\\repositories\\kairo-phantom\\phantom-core\\src\\cua\\cua_executor.rs", "source_location": "L368"}, {"id": "pathbuf", "label": "PathBuf", "file_type": "code", "source_file": "C:\\Users\\praja\\OneDrive\\Desktop\\test-env\\repositories\\kairo-phantom\\phantom-core\\src\\cua\\cua_executor.rs", "source_location": "L368"}, {"id": "cua_cua_executor_verify_action", "label": "verify_action()", "file_type": "code", "source_file": "C:\\Users\\praja\\OneDrive\\Desktop\\test-env\\repositories\\kairo-phantom\\phantom-core\\src\\cua\\cua_executor.rs", "source_location": "L402"}, {"id": "cuaverification", "label": "CuaVerification", "file_type": "code", "source_file": "C:\\Users\\praja\\OneDrive\\Desktop\\test-env\\repositories\\kairo-phantom\\phantom-core\\src\\cua\\cua_executor.rs", "source_location": "L402"}, {"id": "cua_cua_executor_capture_screenshot", "label": "capture_screenshot()", "file_type": "code", "source_file": "C:\\Users\\praja\\OneDrive\\Desktop\\test-env\\repositories\\kairo-phantom\\phantom-core\\src\\cua\\cua_executor.rs", "source_location": "L488"}, {"id": "cua_cua_executor_capture_before_screenshot", "label": "capture_before_screenshot()", "file_type": "code", "source_file": "C:\\Users\\praja\\OneDrive\\Desktop\\test-env\\repositories\\kairo-phantom\\phantom-core\\src\\cua\\cua_executor.rs", "source_location": "L511"}, {"id": "cua_cua_executor_hash_file", "label": "hash_file()", "file_type": "code", "source_file": "C:\\Users\\praja\\OneDrive\\Desktop\\test-env\\repositories\\kairo-phantom\\phantom-core\\src\\cua\\cua_executor.rs", "source_location": "L534"}, {"id": "error", "label": "Error", "file_type": "code", "source_file": "C:\\Users\\praja\\OneDrive\\Desktop\\test-env\\repositories\\kairo-phantom\\phantom-core\\src\\cua\\cua_executor.rs", "source_location": "L534"}, {"id": "cua_cua_executor_audit_log_success", "label": "audit_log_success()", "file_type": "code", "source_file": "C:\\Users\\praja\\OneDrive\\Desktop\\test-env\\repositories\\kairo-phantom\\phantom-core\\src\\cua\\cua_executor.rs", "source_location": "L550"}, {"id": "cua_cua_executor_audit_log_failure", "label": "audit_log_failure()", "file_type": "code", "source_file": "C:\\Users\\praja\\OneDrive\\Desktop\\test-env\\repositories\\kairo-phantom\\phantom-core\\src\\cua\\cua_executor.rs", "source_location": "L555"}, {"id": "cua_cua_executor_audit_log", "label": "audit_log()", "file_type": "code", "source_file": "C:\\Users\\praja\\OneDrive\\Desktop\\test-env\\repositories\\kairo-phantom\\phantom-core\\src\\cua\\cua_executor.rs", "source_location": "L560"}], "edges": [{"source": "c_users_praja_onedrive_desktop_test_env_repositories_kairo_phantom_phantom_core_src_cua_cua_executor_rs", "target": "super", "relation": "imports_from", "confidence": "EXTRACTED", "source_file": "C:\\Users\\praja\\OneDrive\\Desktop\\test-env\\repositories\\kairo-phantom\\phantom-core\\src\\cua\\cua_executor.rs", "source_location": "L8", "weight": 1.0, "context": "import"}, {"source": "c_users_praja_onedrive_desktop_test_env_repositories_kairo_phantom_phantom_core_src_cua_cua_executor_rs", "target": "duration", "relation": "imports_from", "confidence": "EXTRACTED", "source_file": "C:\\Users\\praja\\OneDrive\\Desktop\\test-env\\repositories\\kairo-phantom\\phantom-core\\src\\cua\\cua_executor.rs", "source_location": "L9", "weight": 1.0, "context": "import"}, {"source": "c_users_praja_onedrive_desktop_test_env_repositories_kairo_phantom_phantom_core_src_cua_cua_executor_rs", "target": "cancellationtoken", "relation": "imports_from", "confidence": "EXTRACTED", "source_file": "C:\\Users\\praja\\OneDrive\\Desktop\\test-env\\repositories\\kairo-phantom\\phantom-core\\src\\cua\\cua_executor.rs", "source_location": "L10", "weight": 1.0, "context": "import"}, {"source": "c_users_praja_onedrive_desktop_test_env_repositories_kairo_phantom_phantom_core_src_cua_cua_executor_rs", "target": "cua_cua_executor_executorerror", "relation": "contains", "confidence": "EXTRACTED", "source_file": "C:\\Users\\praja\\OneDrive\\Desktop\\test-env\\repositories\\kairo-phantom\\phantom-core\\src\\cua\\cua_executor.rs", "source_location": "L14", "weight": 1.0}, {"source": "cua_cua_executor_executorerror", "target": "display", "relation": "implements", "confidence": "EXTRACTED", "source_file": "C:\\Users\\praja\\OneDrive\\Desktop\\test-env\\repositories\\kairo-phantom\\phantom-core\\src\\cua\\cua_executor.rs", "source_location": "L22", "weight": 1.0}, {"source": "cua_cua_executor_executorerror", "target": "cua_cua_executor_executorerror_fmt", "relation": "method", "confidence": "EXTRACTED", "source_file": "C:\\Users\\praja\\OneDrive\\Desktop\\test-env\\repositories\\kairo-phantom\\phantom-core\\src\\cua\\cua_executor.rs", "source_location": "L23", "weight": 1.0}, {"source": "cua_cua_executor_executorerror_fmt", "target": "formatter", "relation": "references", "confidence": "EXTRACTED", "source_file": "C:\\Users\\praja\\OneDrive\\Desktop\\test-env\\repositories\\kairo-phantom\\phantom-core\\src\\cua\\cua_executor.rs", "source_location": "L23", "weight": 1.0, "context": "parameter_type"}, {"source": "cua_cua_executor_executorerror_fmt", "target": "result", "relation": "references", "confidence": "EXTRACTED", "source_file": "C:\\Users\\praja\\OneDrive\\Desktop\\test-env\\repositories\\kairo-phantom\\phantom-core\\src\\cua\\cua_executor.rs", "source_location": "L23", "weight": 1.0, "context": "return_type"}, {"source": "c_users_praja_onedrive_desktop_test_env_repositories_kairo_phantom_phantom_core_src_cua_cua_executor_rs", "target": "cua_cua_executor_execute", "relation": "contains", "confidence": "EXTRACTED", "source_file": "C:\\Users\\praja\\OneDrive\\Desktop\\test-env\\repositories\\kairo-phantom\\phantom-core\\src\\cua\\cua_executor.rs", "source_location": "L39", "weight": 1.0}, {"source": "cua_cua_executor_execute", "target": "cuaaction", "relation": "references", "confidence": "EXTRACTED", "source_file": "C:\\Users\\praja\\OneDrive\\Desktop\\test-env\\repositories\\kairo-phantom\\phantom-core\\src\\cua\\cua_executor.rs", "source_location": "L39", "weight": 1.0, "context": "parameter_type"}, {"source": "cua_cua_executor_execute", "target": "cuacontext", "relation": "references", "confidence": "EXTRACTED", "source_file": "C:\\Users\\praja\\OneDrive\\Desktop\\test-env\\repositories\\kairo-phantom\\phantom-core\\src\\cua\\cua_executor.rs", "source_location": "L39", "weight": 1.0, "context": "parameter_type"}, {"source": "cua_cua_executor_execute", "target": "cuabackend", "relation": "references", "confidence": "EXTRACTED", "source_file": "C:\\Users\\praja\\OneDrive\\Desktop\\test-env\\repositories\\kairo-phantom\\phantom-core\\src\\cua\\cua_executor.rs", "source_location": "L39", "weight": 1.0, "context": "parameter_type"}, {"source": "cua_cua_executor_execute", "target": "cancellationtoken", "relation": "references", "confidence": "EXTRACTED", "source_file": "C:\\Users\\praja\\OneDrive\\Desktop\\test-env\\repositories\\kairo-phantom\\phantom-core\\src\\cua\\cua_executor.rs", "source_location": "L39", "weight": 1.0, "context": "parameter_type"}, {"source": "cua_cua_executor_execute", "target": "cuaresult", "relation": "references", "confidence": "EXTRACTED", "source_file": "C:\\Users\\praja\\OneDrive\\Desktop\\test-env\\repositories\\kairo-phantom\\phantom-core\\src\\cua\\cua_executor.rs", "source_location": "L39", "weight": 1.0, "context": "return_type"}, {"source": "c_users_praja_onedrive_desktop_test_env_repositories_kairo_phantom_phantom_core_src_cua_cua_executor_rs", "target": "cua_cua_executor_execute_enigo", "relation": "contains", "confidence": "EXTRACTED", "source_file": "C:\\Users\\praja\\OneDrive\\Desktop\\test-env\\repositories\\kairo-phantom\\phantom-core\\src\\cua\\cua_executor.rs", "source_location": "L140", "weight": 1.0}, {"source": "cua_cua_executor_execute_enigo", "target": "cuaaction", "relation": "references", "confidence": "EXTRACTED", "source_file": "C:\\Users\\praja\\OneDrive\\Desktop\\test-env\\repositories\\kairo-phantom\\phantom-core\\src\\cua\\cua_executor.rs", "source_location": "L140", "weight": 1.0, "context": "parameter_type"}, {"source": "cua_cua_executor_execute_enigo", "target": "cuacontext", "relation": "references", "confidence": "EXTRACTED", "source_file": "C:\\Users\\praja\\OneDrive\\Desktop\\test-env\\repositories\\kairo-phantom\\phantom-core\\src\\cua\\cua_executor.rs", "source_location": "L140", "weight": 1.0, "context": "parameter_type"}, {"source": "cua_cua_executor_execute_enigo", "target": "result", "relation": "references", "confidence": "EXTRACTED", "source_file": "C:\\Users\\praja\\OneDrive\\Desktop\\test-env\\repositories\\kairo-phantom\\phantom-core\\src\\cua\\cua_executor.rs", "source_location": "L140", "weight": 1.0, "context": "return_type"}, {"source": "cua_cua_executor_execute_enigo", "target": "cua_cua_executor_executorerror", "relation": "references", "confidence": "EXTRACTED", "source_file": "C:\\Users\\praja\\OneDrive\\Desktop\\test-env\\repositories\\kairo-phantom\\phantom-core\\src\\cua\\cua_executor.rs", "source_location": "L140", "weight": 1.0, "context": "generic_arg"}, {"source": "c_users_praja_onedrive_desktop_test_env_repositories_kairo_phantom_phantom_core_src_cua_cua_executor_rs", "target": "cua_cua_executor_execute_well_known_shortcut", "relation": "contains", "confidence": "EXTRACTED", "source_file": "C:\\Users\\praja\\OneDrive\\Desktop\\test-env\\repositories\\kairo-phantom\\phantom-core\\src\\cua\\cua_executor.rs", "source_location": "L285", "weight": 1.0}, {"source": "cua_cua_executor_execute_well_known_shortcut", "target": "enigo", "relation": "references", "confidence": "EXTRACTED", "source_file": "C:\\Users\\praja\\OneDrive\\Desktop\\test-env\\repositories\\kairo-phantom\\phantom-core\\src\\cua\\cua_executor.rs", "source_location": "L285", "weight": 1.0, "context": "parameter_type"}, {"source": "cua_cua_executor_execute_well_known_shortcut", "target": "wellknownshortcut", "relation": "references", "confidence": "EXTRACTED", "source_file": "C:\\Users\\praja\\OneDrive\\Desktop\\test-env\\repositories\\kairo-phantom\\phantom-core\\src\\cua\\cua_executor.rs", "source_location": "L285", "weight": 1.0, "context": "parameter_type"}, {"source": "cua_cua_executor_execute_well_known_shortcut", "target": "result", "relation": "references", "confidence": "EXTRACTED", "source_file": "C:\\Users\\praja\\OneDrive\\Desktop\\test-env\\repositories\\kairo-phantom\\phantom-core\\src\\cua\\cua_executor.rs", "source_location": "L285", "weight": 1.0, "context": "return_type"}, {"source": "cua_cua_executor_execute_well_known_shortcut", "target": "string", "relation": "references", "confidence": "EXTRACTED", "source_file": "C:\\Users\\praja\\OneDrive\\Desktop\\test-env\\repositories\\kairo-phantom\\phantom-core\\src\\cua\\cua_executor.rs", "source_location": "L285", "weight": 1.0, "context": "generic_arg"}, {"source": "c_users_praja_onedrive_desktop_test_env_repositories_kairo_phantom_phantom_core_src_cua_cua_executor_rs", "target": "cua_cua_executor_execute_cua_driver", "relation": "contains", "confidence": "EXTRACTED", "source_file": "C:\\Users\\praja\\OneDrive\\Desktop\\test-env\\repositories\\kairo-phantom\\phantom-core\\src\\cua\\cua_executor.rs", "source_location": "L327", "weight": 1.0}, {"source": "cua_cua_executor_execute_cua_driver", "target": "cuaaction", "relation": "references", "confidence": "EXTRACTED", "source_file": "C:\\Users\\praja\\OneDrive\\Desktop\\test-env\\repositories\\kairo-phantom\\phantom-core\\src\\cua\\cua_executor.rs", "source_location": "L327", "weight": 1.0, "context": "parameter_type"}, {"source": "cua_cua_executor_execute_cua_driver", "target": "cuacontext", "relation": "references", "confidence": "EXTRACTED", "source_file": "C:\\Users\\praja\\OneDrive\\Desktop\\test-env\\repositories\\kairo-phantom\\phantom-core\\src\\cua\\cua_executor.rs", "source_location": "L327", "weight": 1.0, "context": "parameter_type"}, {"source": "cua_cua_executor_execute_cua_driver", "target": "result", "relation": "references", "confidence": "EXTRACTED", "source_file": "C:\\Users\\praja\\OneDrive\\Desktop\\test-env\\repositories\\kairo-phantom\\phantom-core\\src\\cua\\cua_executor.rs", "source_location": "L327", "weight": 1.0, "context": "return_type"}, {"source": "cua_cua_executor_execute_cua_driver", "target": "cua_cua_executor_executorerror", "relation": "references", "confidence": "EXTRACTED", "source_file": "C:\\Users\\praja\\OneDrive\\Desktop\\test-env\\repositories\\kairo-phantom\\phantom-core\\src\\cua\\cua_executor.rs", "source_location": "L327", "weight": 1.0, "context": "generic_arg"}, {"source": "c_users_praja_onedrive_desktop_test_env_repositories_kairo_phantom_phantom_core_src_cua_cua_executor_rs", "target": "cua_cua_executor_find_cua_driver", "relation": "contains", "confidence": "EXTRACTED", "source_file": "C:\\Users\\praja\\OneDrive\\Desktop\\test-env\\repositories\\kairo-phantom\\phantom-core\\src\\cua\\cua_executor.rs", "source_location": "L368", "weight": 1.0}, {"source": "cua_cua_executor_find_cua_driver", "target": "option", "relation": "references", "confidence": "EXTRACTED", "source_file": "C:\\Users\\praja\\OneDrive\\Desktop\\test-env\\repositories\\kairo-phantom\\phantom-core\\src\\cua\\cua_executor.rs", "source_location": "L368", "weight": 1.0, "context": "return_type"}, {"source": "cua_cua_executor_find_cua_driver", "target": "pathbuf", "relation": "references", "confidence": "EXTRACTED", "source_file": "C:\\Users\\praja\\OneDrive\\Desktop\\test-env\\repositories\\kairo-phantom\\phantom-core\\src\\cua\\cua_executor.rs", "source_location": "L368", "weight": 1.0, "context": "generic_arg"}, {"source": "c_users_praja_onedrive_desktop_test_env_repositories_kairo_phantom_phantom_core_src_cua_cua_executor_rs", "target": "cua_cua_executor_verify_action", "relation": "contains", "confidence": "EXTRACTED", "source_file": "C:\\Users\\praja\\OneDrive\\Desktop\\test-env\\repositories\\kairo-phantom\\phantom-core\\src\\cua\\cua_executor.rs", "source_location": "L402", "weight": 1.0}, {"source": "cua_cua_executor_verify_action", "target": "cuaaction", "relation": "references", "confidence": "EXTRACTED", "source_file": "C:\\Users\\praja\\OneDrive\\Desktop\\test-env\\repositories\\kairo-phantom\\phantom-core\\src\\cua\\cua_executor.rs", "source_location": "L402", "weight": 1.0, "context": "parameter_type"}, {"source": "cua_cua_executor_verify_action", "target": "cuacontext", "relation": "references", "confidence": "EXTRACTED", "source_file": "C:\\Users\\praja\\OneDrive\\Desktop\\test-env\\repositories\\kairo-phantom\\phantom-core\\src\\cua\\cua_executor.rs", "source_location": "L402", "weight": 1.0, "context": "parameter_type"}, {"source": "cua_cua_executor_verify_action", "target": "result", "relation": "references", "confidence": "EXTRACTED", "source_file": "C:\\Users\\praja\\OneDrive\\Desktop\\test-env\\repositories\\kairo-phantom\\phantom-core\\src\\cua\\cua_executor.rs", "source_location": "L402", "weight": 1.0, "context": "return_type"}, {"source": "cua_cua_executor_verify_action", "target": "cuaverification", "relation": "references", "confidence": "EXTRACTED", "source_file": "C:\\Users\\praja\\OneDrive\\Desktop\\test-env\\repositories\\kairo-phantom\\phantom-core\\src\\cua\\cua_executor.rs", "source_location": "L402", "weight": 1.0, "context": "generic_arg"}, {"source": "cua_cua_executor_verify_action", "target": "cua_cua_executor_executorerror", "relation": "references", "confidence": "EXTRACTED", "source_file": "C:\\Users\\praja\\OneDrive\\Desktop\\test-env\\repositories\\kairo-phantom\\phantom-core\\src\\cua\\cua_executor.rs", "source_location": "L402", "weight": 1.0, "context": "generic_arg"}, {"source": "c_users_praja_onedrive_desktop_test_env_repositories_kairo_phantom_phantom_core_src_cua_cua_executor_rs", "target": "cua_cua_executor_capture_screenshot", "relation": "contains", "confidence": "EXTRACTED", "source_file": "C:\\Users\\praja\\OneDrive\\Desktop\\test-env\\repositories\\kairo-phantom\\phantom-core\\src\\cua\\cua_executor.rs", "source_location": "L488", "weight": 1.0}, {"source": "cua_cua_executor_capture_screenshot", "target": "option", "relation": "references", "confidence": "EXTRACTED", "source_file": "C:\\Users\\praja\\OneDrive\\Desktop\\test-env\\repositories\\kairo-phantom\\phantom-core\\src\\cua\\cua_executor.rs", "source_location": "L488", "weight": 1.0, "context": "return_type"}, {"source": "cua_cua_executor_capture_screenshot", "target": "string", "relation": "references", "confidence": "EXTRACTED", "source_file": "C:\\Users\\praja\\OneDrive\\Desktop\\test-env\\repositories\\kairo-phantom\\phantom-core\\src\\cua\\cua_executor.rs", "source_location": "L488", "weight": 1.0, "context": "generic_arg"}, {"source": "c_users_praja_onedrive_desktop_test_env_repositories_kairo_phantom_phantom_core_src_cua_cua_executor_rs", "target": "cua_cua_executor_capture_before_screenshot", "relation": "contains", "confidence": "EXTRACTED", "source_file": "C:\\Users\\praja\\OneDrive\\Desktop\\test-env\\repositories\\kairo-phantom\\phantom-core\\src\\cua\\cua_executor.rs", "source_location": "L511", "weight": 1.0}, {"source": "cua_cua_executor_capture_before_screenshot", "target": "option", "relation": "references", "confidence": "EXTRACTED", "source_file": "C:\\Users\\praja\\OneDrive\\Desktop\\test-env\\repositories\\kairo-phantom\\phantom-core\\src\\cua\\cua_executor.rs", "source_location": "L511", "weight": 1.0, "context": "return_type"}, {"source": "cua_cua_executor_capture_before_screenshot", "target": "string", "relation": "references", "confidence": "EXTRACTED", "source_file": "C:\\Users\\praja\\OneDrive\\Desktop\\test-env\\repositories\\kairo-phantom\\phantom-core\\src\\cua\\cua_executor.rs", "source_location": "L511", "weight": 1.0, "context": "generic_arg"}, {"source": "c_users_praja_onedrive_desktop_test_env_repositories_kairo_phantom_phantom_core_src_cua_cua_executor_rs", "target": "cua_cua_executor_hash_file", "relation": "contains", "confidence": "EXTRACTED", "source_file": "C:\\Users\\praja\\OneDrive\\Desktop\\test-env\\repositories\\kairo-phantom\\phantom-core\\src\\cua\\cua_executor.rs", "source_location": "L534", "weight": 1.0}, {"source": "cua_cua_executor_hash_file", "target": "result", "relation": "references", "confidence": "EXTRACTED", "source_file": "C:\\Users\\praja\\OneDrive\\Desktop\\test-env\\repositories\\kairo-phantom\\phantom-core\\src\\cua\\cua_executor.rs", "source_location": "L534", "weight": 1.0, "context": "return_type"}, {"source": "cua_cua_executor_hash_file", "target": "string", "relation": "references", "confidence": "EXTRACTED", "source_file": "C:\\Users\\praja\\OneDrive\\Desktop\\test-env\\repositories\\kairo-phantom\\phantom-core\\src\\cua\\cua_executor.rs", "source_location": "L534", "weight": 1.0, "context": "generic_arg"}, {"source": "cua_cua_executor_hash_file", "target": "error", "relation": "references", "confidence": "EXTRACTED", "source_file": "C:\\Users\\praja\\OneDrive\\Desktop\\test-env\\repositories\\kairo-phantom\\phantom-core\\src\\cua\\cua_executor.rs", "source_location": "L534", "weight": 1.0, "context": "generic_arg"}, {"source": "c_users_praja_onedrive_desktop_test_env_repositories_kairo_phantom_phantom_core_src_cua_cua_executor_rs", "target": "cua_cua_executor_audit_log_success", "relation": "contains", "confidence": "EXTRACTED", "source_file": "C:\\Users\\praja\\OneDrive\\Desktop\\test-env\\repositories\\kairo-phantom\\phantom-core\\src\\cua\\cua_executor.rs", "source_location": "L550", "weight": 1.0}, {"source": "cua_cua_executor_audit_log_success", "target": "cuaaction", "relation": "references", "confidence": "EXTRACTED", "source_file": "C:\\Users\\praja\\OneDrive\\Desktop\\test-env\\repositories\\kairo-phantom\\phantom-core\\src\\cua\\cua_executor.rs", "source_location": "L550", "weight": 1.0, "context": "parameter_type"}, {"source": "cua_cua_executor_audit_log_success", "target": "cuacontext", "relation": "references", "confidence": "EXTRACTED", "source_file": "C:\\Users\\praja\\OneDrive\\Desktop\\test-env\\repositories\\kairo-phantom\\phantom-core\\src\\cua\\cua_executor.rs", "source_location": "L550", "weight": 1.0, "context": "parameter_type"}, {"source": "cua_cua_executor_audit_log_success", "target": "cuaverification", "relation": "references", "confidence": "EXTRACTED", "source_file": "C:\\Users\\praja\\OneDrive\\Desktop\\test-env\\repositories\\kairo-phantom\\phantom-core\\src\\cua\\cua_executor.rs", "source_location": "L550", "weight": 1.0, "context": "parameter_type"}, {"source": "c_users_praja_onedrive_desktop_test_env_repositories_kairo_phantom_phantom_core_src_cua_cua_executor_rs", "target": "cua_cua_executor_audit_log_failure", "relation": "contains", "confidence": "EXTRACTED", "source_file": "C:\\Users\\praja\\OneDrive\\Desktop\\test-env\\repositories\\kairo-phantom\\phantom-core\\src\\cua\\cua_executor.rs", "source_location": "L555", "weight": 1.0}, {"source": "cua_cua_executor_audit_log_failure", "target": "cuaaction", "relation": "references", "confidence": "EXTRACTED", "source_file": "C:\\Users\\praja\\OneDrive\\Desktop\\test-env\\repositories\\kairo-phantom\\phantom-core\\src\\cua\\cua_executor.rs", "source_location": "L555", "weight": 1.0, "context": "parameter_type"}, {"source": "cua_cua_executor_audit_log_failure", "target": "cuacontext", "relation": "references", "confidence": "EXTRACTED", "source_file": "C:\\Users\\praja\\OneDrive\\Desktop\\test-env\\repositories\\kairo-phantom\\phantom-core\\src\\cua\\cua_executor.rs", "source_location": "L555", "weight": 1.0, "context": "parameter_type"}, {"source": "c_users_praja_onedrive_desktop_test_env_repositories_kairo_phantom_phantom_core_src_cua_cua_executor_rs", "target": "cua_cua_executor_audit_log", "relation": "contains", "confidence": "EXTRACTED", "source_file": "C:\\Users\\praja\\OneDrive\\Desktop\\test-env\\repositories\\kairo-phantom\\phantom-core\\src\\cua\\cua_executor.rs", "source_location": "L560", "weight": 1.0}, {"source": "cua_cua_executor_audit_log", "target": "cuaaction", "relation": "references", "confidence": "EXTRACTED", "source_file": "C:\\Users\\praja\\OneDrive\\Desktop\\test-env\\repositories\\kairo-phantom\\phantom-core\\src\\cua\\cua_executor.rs", "source_location": "L560", "weight": 1.0, "context": "parameter_type"}, {"source": "cua_cua_executor_audit_log", "target": "cuacontext", "relation": "references", "confidence": "EXTRACTED", "source_file": "C:\\Users\\praja\\OneDrive\\Desktop\\test-env\\repositories\\kairo-phantom\\phantom-core\\src\\cua\\cua_executor.rs", "source_location": "L560", "weight": 1.0, "context": "parameter_type"}, {"source": "cua_cua_executor_audit_log", "target": "option", "relation": "references", "confidence": "EXTRACTED", "source_file": "C:\\Users\\praja\\OneDrive\\Desktop\\test-env\\repositories\\kairo-phantom\\phantom-core\\src\\cua\\cua_executor.rs", "source_location": "L560", "weight": 1.0, "context": "parameter_type"}, {"source": "c_users_praja_onedrive_desktop_test_env_repositories_kairo_phantom_phantom_core_src_cua_cua_executor_rs", "target": "axis", "relation": "imports_from", "confidence": "EXTRACTED", "source_file": "C:\\Users\\praja\\OneDrive\\Desktop\\test-env\\repositories\\kairo-phantom\\phantom-core\\src\\cua\\cua_executor.rs", "source_location": "L602", "weight": 1.0, "context": "import"}, {"source": "cua_cua_executor_execute", "target": "cua_cua_executor_capture_before_screenshot", "relation": "calls", "context": "call", "confidence": "EXTRACTED", "source_file": "C:\\Users\\praja\\OneDrive\\Desktop\\test-env\\repositories\\kairo-phantom\\phantom-core\\src\\cua\\cua_executor.rs", "source_location": "L61", "weight": 1.0}, {"source": "cua_cua_executor_execute", "target": "cua_cua_executor_execute_enigo", "relation": "calls", "context": "call", "confidence": "EXTRACTED", "source_file": "C:\\Users\\praja\\OneDrive\\Desktop\\test-env\\repositories\\kairo-phantom\\phantom-core\\src\\cua\\cua_executor.rs", "source_location": "L83", "weight": 1.0}, {"source": "cua_cua_executor_execute", "target": "cua_cua_executor_execute_cua_driver", "relation": "calls", "context": "call", "confidence": "EXTRACTED", "source_file": "C:\\Users\\praja\\OneDrive\\Desktop\\test-env\\repositories\\kairo-phantom\\phantom-core\\src\\cua\\cua_executor.rs", "source_location": "L84", "weight": 1.0}, {"source": "cua_cua_executor_execute", "target": "cua_cua_executor_verify_action", "relation": "calls", "context": "call", "confidence": "EXTRACTED", "source_file": "C:\\Users\\praja\\OneDrive\\Desktop\\test-env\\repositories\\kairo-phantom\\phantom-core\\src\\cua\\cua_executor.rs", "source_location": "L90", "weight": 1.0}, {"source": "cua_cua_executor_execute", "target": "cua_cua_executor_audit_log_success", "relation": "calls", "context": "call", "confidence": "EXTRACTED", "source_file": "C:\\Users\\praja\\OneDrive\\Desktop\\test-env\\repositories\\kairo-phantom\\phantom-core\\src\\cua\\cua_executor.rs", "source_location": "L94", "weight": 1.0}, {"source": "cua_cua_executor_execute", "target": "cua_cua_executor_audit_log_failure", "relation": "calls", "context": "call", "confidence": "EXTRACTED", "source_file": "C:\\Users\\praja\\OneDrive\\Desktop\\test-env\\repositories\\kairo-phantom\\phantom-core\\src\\cua\\cua_executor.rs", "source_location": "L104", "weight": 1.0}, {"source": "cua_cua_executor_execute_enigo", "target": "cua_cua_executor_execute_well_known_shortcut", "relation": "calls", "context": "call", "confidence": "EXTRACTED", "source_file": "C:\\Users\\praja\\OneDrive\\Desktop\\test-env\\repositories\\kairo-phantom\\phantom-core\\src\\cua\\cua_executor.rs", "source_location": "L272", "weight": 1.0}, {"source": "cua_cua_executor_execute_cua_driver", "target": "cua_cua_executor_find_cua_driver", "relation": "calls", "context": "call", "confidence": "EXTRACTED", "source_file": "C:\\Users\\praja\\OneDrive\\Desktop\\test-env\\repositories\\kairo-phantom\\phantom-core\\src\\cua\\cua_executor.rs", "source_location": "L330", "weight": 1.0}, {"source": "cua_cua_executor_verify_action", "target": "cua_cua_executor_capture_screenshot", "relation": "calls", "context": "call", "confidence": "EXTRACTED", "source_file": "C:\\Users\\praja\\OneDrive\\Desktop\\test-env\\repositories\\kairo-phantom\\phantom-core\\src\\cua\\cua_executor.rs", "source_location": "L407", "weight": 1.0}, {"source": "cua_cua_executor_verify_action", "target": "cua_cua_executor_hash_file", "relation": "calls", "context": "call", "confidence": "EXTRACTED", "source_file": "C:\\Users\\praja\\OneDrive\\Desktop\\test-env\\repositories\\kairo-phantom\\phantom-core\\src\\cua\\cua_executor.rs", "source_location": "L412", "weight": 1.0}, {"source": "cua_cua_executor_audit_log_success", "target": "cua_cua_executor_audit_log", "relation": "calls", "context": "call", "confidence": "EXTRACTED", "source_file": "C:\\Users\\praja\\OneDrive\\Desktop\\test-env\\repositories\\kairo-phantom\\phantom-core\\src\\cua\\cua_executor.rs", "source_location": "L551", "weight": 1.0}, {"source": "cua_cua_executor_audit_log_failure", "target": "cua_cua_executor_audit_log", "relation": "calls", "context": "call", "confidence": "EXTRACTED", "source_file": "C:\\Users\\praja\\OneDrive\\Desktop\\test-env\\repositories\\kairo-phantom\\phantom-core\\src\\cua\\cua_executor.rs", "source_location": "L556", "weight": 1.0}], "raw_calls": [{"caller_nid": "cua_cua_executor_execute", "callee": "is_cancelled", "is_member_call": true, "source_file": "C:\\Users\\praja\\OneDrive\\Desktop\\test-env\\repositories\\kairo-phantom\\phantom-core\\src\\cua\\cua_executor.rs", "source_location": "L46"}, {"caller_nid": "cua_cua_executor_execute", "callee": "drop", "is_member_call": false, "source_file": "C:\\Users\\praja\\OneDrive\\Desktop\\test-env\\repositories\\kairo-phantom\\phantom-core\\src\\cua\\cua_executor.rs", "source_location": "L56"}, {"caller_nid": "cua_cua_executor_execute", "callee": "is_none", "is_member_call": true, "source_file": "C:\\Users\\praja\\OneDrive\\Desktop\\test-env\\repositories\\kairo-phantom\\phantom-core\\src\\cua\\cua_executor.rs", "source_location": "L60"}, {"caller_nid": "cua_cua_executor_execute", "callee": "is_cancelled", "is_member_call": true, "source_file": "C:\\Users\\praja\\OneDrive\\Desktop\\test-env\\repositories\\kairo-phantom\\phantom-core\\src\\cua\\cua_executor.rs", "source_location": "L68"}, {"caller_nid": "cua_cua_executor_execute", "callee": "is_cancelled", "is_member_call": true, "source_file": "C:\\Users\\praja\\OneDrive\\Desktop\\test-env\\repositories\\kairo-phantom\\phantom-core\\src\\cua\\cua_executor.rs", "source_location": "L77"}, {"caller_nid": "cua_cua_executor_execute", "callee": "fallback", "is_member_call": true, "source_file": "C:\\Users\\praja\\OneDrive\\Desktop\\test-env\\repositories\\kairo-phantom\\phantom-core\\src\\cua\\cua_executor.rs", "source_location": "L100"}, {"caller_nid": "cua_cua_executor_execute", "callee": "fallback", "is_member_call": true, "source_file": "C:\\Users\\praja\\OneDrive\\Desktop\\test-env\\repositories\\kairo-phantom\\phantom-core\\src\\cua\\cua_executor.rs", "source_location": "L126"}, {"caller_nid": "cua_cua_executor_execute_enigo", "callee": "map_err", "is_member_call": true, "source_file": "C:\\Users\\praja\\OneDrive\\Desktop\\test-env\\repositories\\kairo-phantom\\phantom-core\\src\\cua\\cua_executor.rs", "source_location": "L143"}, {"caller_nid": "cua_cua_executor_execute_enigo", "callee": "map_err", "is_member_call": true, "source_file": "C:\\Users\\praja\\OneDrive\\Desktop\\test-env\\repositories\\kairo-phantom\\phantom-core\\src\\cua\\cua_executor.rs", "source_location": "L152"}, {"caller_nid": "cua_cua_executor_execute_enigo", "callee": "move_mouse", "is_member_call": true, "source_file": "C:\\Users\\praja\\OneDrive\\Desktop\\test-env\\repositories\\kairo-phantom\\phantom-core\\src\\cua\\cua_executor.rs", "source_location": "L152"}, {"caller_nid": "cua_cua_executor_execute_enigo", "callee": "map_err", "is_member_call": true, "source_file": "C:\\Users\\praja\\OneDrive\\Desktop\\test-env\\repositories\\kairo-phantom\\phantom-core\\src\\cua\\cua_executor.rs", "source_location": "L164"}, {"caller_nid": "cua_cua_executor_execute_enigo", "callee": "button", "is_member_call": true, "source_file": "C:\\Users\\praja\\OneDrive\\Desktop\\test-env\\repositories\\kairo-phantom\\phantom-core\\src\\cua\\cua_executor.rs", "source_location": "L164"}, {"caller_nid": "cua_cua_executor_execute_enigo", "callee": "map_err", "is_member_call": true, "source_file": "C:\\Users\\praja\\OneDrive\\Desktop\\test-env\\repositories\\kairo-phantom\\phantom-core\\src\\cua\\cua_executor.rs", "source_location": "L173"}, {"caller_nid": "cua_cua_executor_execute_enigo", "callee": "move_mouse", "is_member_call": true, "source_file": "C:\\Users\\praja\\OneDrive\\Desktop\\test-env\\repositories\\kairo-phantom\\phantom-core\\src\\cua\\cua_executor.rs", "source_location": "L173"}, {"caller_nid": "cua_cua_executor_execute_enigo", "callee": "map_err", "is_member_call": true, "source_file": "C:\\Users\\praja\\OneDrive\\Desktop\\test-env\\repositories\\kairo-phantom\\phantom-core\\src\\cua\\cua_executor.rs", "source_location": "L183"}, {"caller_nid": "cua_cua_executor_execute_enigo", "callee": "button", "is_member_call": true, "source_file": "C:\\Users\\praja\\OneDrive\\Desktop\\test-env\\repositories\\kairo-phantom\\phantom-core\\src\\cua\\cua_executor.rs", "source_location": "L183"}, {"caller_nid": "cua_cua_executor_execute_enigo", "callee": "map_err", "is_member_call": true, "source_file": "C:\\Users\\praja\\OneDrive\\Desktop\\test-env\\repositories\\kairo-phantom\\phantom-core\\src\\cua\\cua_executor.rs", "source_location": "L187"}, {"caller_nid": "cua_cua_executor_execute_enigo", "callee": "button", "is_member_call": true, "source_file": "C:\\Users\\praja\\OneDrive\\Desktop\\test-env\\repositories\\kairo-phantom\\phantom-core\\src\\cua\\cua_executor.rs", "source_location": "L187"}, {"caller_nid": "cua_cua_executor_execute_enigo", "callee": "map_err", "is_member_call": true, "source_file": "C:\\Users\\praja\\OneDrive\\Desktop\\test-env\\repositories\\kairo-phantom\\phantom-core\\src\\cua\\cua_executor.rs", "source_location": "L195"}, {"caller_nid": "cua_cua_executor_execute_enigo", "callee": "move_mouse", "is_member_call": true, "source_file": "C:\\Users\\praja\\OneDrive\\Desktop\\test-env\\repositories\\kairo-phantom\\phantom-core\\src\\cua\\cua_executor.rs", "source_location": "L195"}, {"caller_nid": "cua_cua_executor_execute_enigo", "callee": "map_err", "is_member_call": true, "source_file": "C:\\Users\\praja\\OneDrive\\Desktop\\test-env\\repositories\\kairo-phantom\\phantom-core\\src\\cua\\cua_executor.rs", "source_location": "L208"}, {"caller_nid": "cua_cua_executor_execute_enigo", "callee": "scroll", "is_member_call": true, "source_file": "C:\\Users\\praja\\OneDrive\\Desktop\\test-env\\repositories\\kairo-phantom\\phantom-core\\src\\cua\\cua_executor.rs", "source_location": "L208"}, {"caller_nid": "cua_cua_executor_execute_enigo", "callee": "map_err", "is_member_call": true, "source_file": "C:\\Users\\praja\\OneDrive\\Desktop\\test-env\\repositories\\kairo-phantom\\phantom-core\\src\\cua\\cua_executor.rs", "source_location": "L213"}, {"caller_nid": "cua_cua_executor_execute_enigo", "callee": "scroll", "is_member_call": true, "source_file": "C:\\Users\\praja\\OneDrive\\Desktop\\test-env\\repositories\\kairo-phantom\\phantom-core\\src\\cua\\cua_executor.rs", "source_location": "L213"}, {"caller_nid": "cua_cua_executor_execute_enigo", "callee": "map_err", "is_member_call": true, "source_file": "C:\\Users\\praja\\OneDrive\\Desktop\\test-env\\repositories\\kairo-phantom\\phantom-core\\src\\cua\\cua_executor.rs", "source_location": "L222"}, {"caller_nid": "cua_cua_executor_execute_enigo", "callee": "text", "is_member_call": true, "source_file": "C:\\Users\\praja\\OneDrive\\Desktop\\test-env\\repositories\\kairo-phantom\\phantom-core\\src\\cua\\cua_executor.rs", "source_location": "L222"}, {"caller_nid": "cua_cua_executor_execute_enigo", "callee": "chars", "is_member_call": true, "source_file": "C:\\Users\\praja\\OneDrive\\Desktop\\test-env\\repositories\\kairo-phantom\\phantom-core\\src\\cua\\cua_executor.rs", "source_location": "L226"}, {"caller_nid": "cua_cua_executor_execute_enigo", "callee": "chunks", "is_member_call": true, "source_file": "C:\\Users\\praja\\OneDrive\\Desktop\\test-env\\repositories\\kairo-phantom\\phantom-core\\src\\cua\\cua_executor.rs", "source_location": "L227"}, {"caller_nid": "cua_cua_executor_execute_enigo", "callee": "map_err", "is_member_call": true, "source_file": "C:\\Users\\praja\\OneDrive\\Desktop\\test-env\\repositories\\kairo-phantom\\phantom-core\\src\\cua\\cua_executor.rs", "source_location": "L229"}, {"caller_nid": "cua_cua_executor_execute_enigo", "callee": "text", "is_member_call": true, "source_file": "C:\\Users\\praja\\OneDrive\\Desktop\\test-env\\repositories\\kairo-phantom\\phantom-core\\src\\cua\\cua_executor.rs", "source_location": "L229"}, {"caller_nid": "cua_cua_executor_execute_enigo", "callee": "as_str", "is_member_call": true, "source_file": "C:\\Users\\praja\\OneDrive\\Desktop\\test-env\\repositories\\kairo-phantom\\phantom-core\\src\\cua\\cua_executor.rs", "source_location": "L242"}, {"caller_nid": "cua_cua_executor_execute_enigo", "callee": "to_lowercase", "is_member_call": true, "source_file": "C:\\Users\\praja\\OneDrive\\Desktop\\test-env\\repositories\\kairo-phantom\\phantom-core\\src\\cua\\cua_executor.rs", "source_location": "L242"}, {"caller_nid": "cua_cua_executor_execute_enigo", "callee": "chars", "is_member_call": true, "source_file": "C:\\Users\\praja\\OneDrive\\Desktop\\test-env\\repositories\\kairo-phantom\\phantom-core\\src\\cua\\cua_executor.rs", "source_location": "L248"}, {"caller_nid": "cua_cua_executor_execute_enigo", "callee": "map_err", "is_member_call": true, "source_file": "C:\\Users\\praja\\OneDrive\\Desktop\\test-env\\repositories\\kairo-phantom\\phantom-core\\src\\cua\\cua_executor.rs", "source_location": "L255"}, {"caller_nid": "cua_cua_executor_execute_enigo", "callee": "key", "is_member_call": true, "source_file": "C:\\Users\\praja\\OneDrive\\Desktop\\test-env\\repositories\\kairo-phantom\\phantom-core\\src\\cua\\cua_executor.rs", "source_location": "L255"}, {"caller_nid": "cua_cua_executor_execute_enigo", "callee": "map_err", "is_member_call": true, "source_file": "C:\\Users\\praja\\OneDrive\\Desktop\\test-env\\repositories\\kairo-phantom\\phantom-core\\src\\cua\\cua_executor.rs", "source_location": "L260"}, {"caller_nid": "cua_cua_executor_execute_enigo", "callee": "key", "is_member_call": true, "source_file": "C:\\Users\\praja\\OneDrive\\Desktop\\test-env\\repositories\\kairo-phantom\\phantom-core\\src\\cua\\cua_executor.rs", "source_location": "L260"}, {"caller_nid": "cua_cua_executor_execute_enigo", "callee": "rev", "is_member_call": true, "source_file": "C:\\Users\\praja\\OneDrive\\Desktop\\test-env\\repositories\\kairo-phantom\\phantom-core\\src\\cua\\cua_executor.rs", "source_location": "L264"}, {"caller_nid": "cua_cua_executor_execute_enigo", "callee": "map_err", "is_member_call": true, "source_file": "C:\\Users\\praja\\OneDrive\\Desktop\\test-env\\repositories\\kairo-phantom\\phantom-core\\src\\cua\\cua_executor.rs", "source_location": "L265"}, {"caller_nid": "cua_cua_executor_execute_enigo", "callee": "key", "is_member_call": true, "source_file": "C:\\Users\\praja\\OneDrive\\Desktop\\test-env\\repositories\\kairo-phantom\\phantom-core\\src\\cua\\cua_executor.rs", "source_location": "L265"}, {"caller_nid": "cua_cua_executor_execute_enigo", "callee": "map_err", "is_member_call": true, "source_file": "C:\\Users\\praja\\OneDrive\\Desktop\\test-env\\repositories\\kairo-phantom\\phantom-core\\src\\cua\\cua_executor.rs", "source_location": "L272"}, {"caller_nid": "cua_cua_executor_execute_well_known_shortcut", "callee": "map_err", "is_member_call": true, "source_file": "C:\\Users\\praja\\OneDrive\\Desktop\\test-env\\repositories\\kairo-phantom\\phantom-core\\src\\cua\\cua_executor.rs", "source_location": "L292"}, {"caller_nid": "cua_cua_executor_execute_well_known_shortcut", "callee": "key", "is_member_call": true, "source_file": "C:\\Users\\praja\\OneDrive\\Desktop\\test-env\\repositories\\kairo-phantom\\phantom-core\\src\\cua\\cua_executor.rs", "source_location": "L292"}, {"caller_nid": "cua_cua_executor_execute_well_known_shortcut", "callee": "map_err", "is_member_call": true, "source_file": "C:\\Users\\praja\\OneDrive\\Desktop\\test-env\\repositories\\kairo-phantom\\phantom-core\\src\\cua\\cua_executor.rs", "source_location": "L293"}, {"caller_nid": "cua_cua_executor_execute_well_known_shortcut", "callee": "key", "is_member_call": true, "source_file": "C:\\Users\\praja\\OneDrive\\Desktop\\test-env\\repositories\\kairo-phantom\\phantom-core\\src\\cua\\cua_executor.rs", "source_location": "L293"}, {"caller_nid": "cua_cua_executor_execute_well_known_shortcut", "callee": "map_err", "is_member_call": true, "source_file": "C:\\Users\\praja\\OneDrive\\Desktop\\test-env\\repositories\\kairo-phantom\\phantom-core\\src\\cua\\cua_executor.rs", "source_location": "L294"}, {"caller_nid": "cua_cua_executor_execute_well_known_shortcut", "callee": "key", "is_member_call": true, "source_file": "C:\\Users\\praja\\OneDrive\\Desktop\\test-env\\repositories\\kairo-phantom\\phantom-core\\src\\cua\\cua_executor.rs", "source_location": "L294"}, {"caller_nid": "cua_cua_executor_execute_well_known_shortcut", "callee": "map_err", "is_member_call": true, "source_file": "C:\\Users\\praja\\OneDrive\\Desktop\\test-env\\repositories\\kairo-phantom\\phantom-core\\src\\cua\\cua_executor.rs", "source_location": "L299"}, {"caller_nid": "cua_cua_executor_execute_well_known_shortcut", "callee": "key", "is_member_call": true, "source_file": "C:\\Users\\praja\\OneDrive\\Desktop\\test-env\\repositories\\kairo-phantom\\phantom-core\\src\\cua\\cua_executor.rs", "source_location": "L299"}, {"caller_nid": "cua_cua_executor_execute_well_known_shortcut", "callee": "map_err", "is_member_call": true, "source_file": "C:\\Users\\praja\\OneDrive\\Desktop\\test-env\\repositories\\kairo-phantom\\phantom-core\\src\\cua\\cua_executor.rs", "source_location": "L300"}, {"caller_nid": "cua_cua_executor_execute_well_known_shortcut", "callee": "key", "is_member_call": true, "source_file": "C:\\Users\\praja\\OneDrive\\Desktop\\test-env\\repositories\\kairo-phantom\\phantom-core\\src\\cua\\cua_executor.rs", "source_location": "L300"}, {"caller_nid": "cua_cua_executor_execute_well_known_shortcut", "callee": "map_err", "is_member_call": true, "source_file": "C:\\Users\\praja\\OneDrive\\Desktop\\test-env\\repositories\\kairo-phantom\\phantom-core\\src\\cua\\cua_executor.rs", "source_location": "L301"}, {"caller_nid": "cua_cua_executor_execute_well_known_shortcut", "callee": "key", "is_member_call": true, "source_file": "C:\\Users\\praja\\OneDrive\\Desktop\\test-env\\repositories\\kairo-phantom\\phantom-core\\src\\cua\\cua_executor.rs", "source_location": "L301"}, {"caller_nid": "cua_cua_executor_execute_well_known_shortcut", "callee": "map_err", "is_member_call": true, "source_file": "C:\\Users\\praja\\OneDrive\\Desktop\\test-env\\repositories\\kairo-phantom\\phantom-core\\src\\cua\\cua_executor.rs", "source_location": "L302"}, {"caller_nid": "cua_cua_executor_execute_well_known_shortcut", "callee": "key", "is_member_call": true, "source_file": "C:\\Users\\praja\\OneDrive\\Desktop\\test-env\\repositories\\kairo-phantom\\phantom-core\\src\\cua\\cua_executor.rs", "source_location": "L302"}, {"caller_nid": "cua_cua_executor_execute_well_known_shortcut", "callee": "map_err", "is_member_call": true, "source_file": "C:\\Users\\praja\\OneDrive\\Desktop\\test-env\\repositories\\kairo-phantom\\phantom-core\\src\\cua\\cua_executor.rs", "source_location": "L303"}, {"caller_nid": "cua_cua_executor_execute_well_known_shortcut", "callee": "key", "is_member_call": true, "source_file": "C:\\Users\\praja\\OneDrive\\Desktop\\test-env\\repositories\\kairo-phantom\\phantom-core\\src\\cua\\cua_executor.rs", "source_location": "L303"}, {"caller_nid": "cua_cua_executor_execute_well_known_shortcut", "callee": "press_ctrl_shift", "is_member_call": false, "source_file": "C:\\Users\\praja\\OneDrive\\Desktop\\test-env\\repositories\\kairo-phantom\\phantom-core\\src\\cua\\cua_executor.rs", "source_location": "L308"}, {"caller_nid": "cua_cua_executor_execute_well_known_shortcut", "callee": "press_ctrl_shift", "is_member_call": false, "source_file": "C:\\Users\\praja\\OneDrive\\Desktop\\test-env\\repositories\\kairo-phantom\\phantom-core\\src\\cua\\cua_executor.rs", "source_location": "L309"}, {"caller_nid": "cua_cua_executor_execute_well_known_shortcut", "callee": "press_ctrl", "is_member_call": false, "source_file": "C:\\Users\\praja\\OneDrive\\Desktop\\test-env\\repositories\\kairo-phantom\\phantom-core\\src\\cua\\cua_executor.rs", "source_location": "L310"}, {"caller_nid": "cua_cua_executor_execute_well_known_shortcut", "callee": "press_ctrl", "is_member_call": false, "source_file": "C:\\Users\\praja\\OneDrive\\Desktop\\test-env\\repositories\\kairo-phantom\\phantom-core\\src\\cua\\cua_executor.rs", "source_location": "L311"}, {"caller_nid": "cua_cua_executor_execute_well_known_shortcut", "callee": "press_ctrl", "is_member_call": false, "source_file": "C:\\Users\\praja\\OneDrive\\Desktop\\test-env\\repositories\\kairo-phantom\\phantom-core\\src\\cua\\cua_executor.rs", "source_location": "L312"}, {"caller_nid": "cua_cua_executor_execute_well_known_shortcut", "callee": "map_err", "is_member_call": true, "source_file": "C:\\Users\\praja\\OneDrive\\Desktop\\test-env\\repositories\\kairo-phantom\\phantom-core\\src\\cua\\cua_executor.rs", "source_location": "L314"}, {"caller_nid": "cua_cua_executor_execute_well_known_shortcut", "callee": "key", "is_member_call": true, "source_file": "C:\\Users\\praja\\OneDrive\\Desktop\\test-env\\repositories\\kairo-phantom\\phantom-core\\src\\cua\\cua_executor.rs", "source_location": "L314"}, {"caller_nid": "cua_cua_executor_execute_well_known_shortcut", "callee": "map_err", "is_member_call": true, "source_file": "C:\\Users\\praja\\OneDrive\\Desktop\\test-env\\repositories\\kairo-phantom\\phantom-core\\src\\cua\\cua_executor.rs", "source_location": "L317"}, {"caller_nid": "cua_cua_executor_execute_well_known_shortcut", "callee": "key", "is_member_call": true, "source_file": "C:\\Users\\praja\\OneDrive\\Desktop\\test-env\\repositories\\kairo-phantom\\phantom-core\\src\\cua\\cua_executor.rs", "source_location": "L317"}, {"caller_nid": "cua_cua_executor_execute_well_known_shortcut", "callee": "map_err", "is_member_call": true, "source_file": "C:\\Users\\praja\\OneDrive\\Desktop\\test-env\\repositories\\kairo-phantom\\phantom-core\\src\\cua\\cua_executor.rs", "source_location": "L320"}, {"caller_nid": "cua_cua_executor_execute_well_known_shortcut", "callee": "key", "is_member_call": true, "source_file": "C:\\Users\\praja\\OneDrive\\Desktop\\test-env\\repositories\\kairo-phantom\\phantom-core\\src\\cua\\cua_executor.rs", "source_location": "L320"}, {"caller_nid": "cua_cua_executor_execute_cua_driver", "callee": "ok_or", "is_member_call": true, "source_file": "C:\\Users\\praja\\OneDrive\\Desktop\\test-env\\repositories\\kairo-phantom\\phantom-core\\src\\cua\\cua_executor.rs", "source_location": "L330"}, {"caller_nid": "cua_cua_executor_execute_cua_driver", "callee": "output", "is_member_call": true, "source_file": "C:\\Users\\praja\\OneDrive\\Desktop\\test-env\\repositories\\kairo-phantom\\phantom-core\\src\\cua\\cua_executor.rs", "source_location": "L336"}, {"caller_nid": "cua_cua_executor_execute_cua_driver", "callee": "args", "is_member_call": true, "source_file": "C:\\Users\\praja\\OneDrive\\Desktop\\test-env\\repositories\\kairo-phantom\\phantom-core\\src\\cua\\cua_executor.rs", "source_location": "L336"}, {"caller_nid": "cua_cua_executor_execute_cua_driver", "callee": "output", "is_member_call": true, "source_file": "C:\\Users\\praja\\OneDrive\\Desktop\\test-env\\repositories\\kairo-phantom\\phantom-core\\src\\cua\\cua_executor.rs", "source_location": "L341"}, {"caller_nid": "cua_cua_executor_execute_cua_driver", "callee": "args", "is_member_call": true, "source_file": "C:\\Users\\praja\\OneDrive\\Desktop\\test-env\\repositories\\kairo-phantom\\phantom-core\\src\\cua\\cua_executor.rs", "source_location": "L341"}, {"caller_nid": "cua_cua_executor_execute_cua_driver", "callee": "output", "is_member_call": true, "source_file": "C:\\Users\\praja\\OneDrive\\Desktop\\test-env\\repositories\\kairo-phantom\\phantom-core\\src\\cua\\cua_executor.rs", "source_location": "L348"}, {"caller_nid": "cua_cua_executor_execute_cua_driver", "callee": "args", "is_member_call": true, "source_file": "C:\\Users\\praja\\OneDrive\\Desktop\\test-env\\repositories\\kairo-phantom\\phantom-core\\src\\cua\\cua_executor.rs", "source_location": "L348"}, {"caller_nid": "cua_cua_executor_execute_cua_driver", "callee": "success", "is_member_call": true, "source_file": "C:\\Users\\praja\\OneDrive\\Desktop\\test-env\\repositories\\kairo-phantom\\phantom-core\\src\\cua\\cua_executor.rs", "source_location": "L359"}, {"caller_nid": "cua_cua_executor_find_cua_driver", "callee": "join", "is_member_call": true, "source_file": "C:\\Users\\praja\\OneDrive\\Desktop\\test-env\\repositories\\kairo-phantom\\phantom-core\\src\\cua\\cua_executor.rs", "source_location": "L370"}, {"caller_nid": "cua_cua_executor_find_cua_driver", "callee": "join", "is_member_call": true, "source_file": "C:\\Users\\praja\\OneDrive\\Desktop\\test-env\\repositories\\kairo-phantom\\phantom-core\\src\\cua\\cua_executor.rs", "source_location": "L370"}, {"caller_nid": "cua_cua_executor_find_cua_driver", "callee": "join", "is_member_call": true, "source_file": "C:\\Users\\praja\\OneDrive\\Desktop\\test-env\\repositories\\kairo-phantom\\phantom-core\\src\\cua\\cua_executor.rs", "source_location": "L370"}, {"caller_nid": "cua_cua_executor_find_cua_driver", "callee": "join", "is_member_call": true, "source_file": "C:\\Users\\praja\\OneDrive\\Desktop\\test-env\\repositories\\kairo-phantom\\phantom-core\\src\\cua\\cua_executor.rs", "source_location": "L370"}, {"caller_nid": "cua_cua_executor_find_cua_driver", "callee": "join", "is_member_call": true, "source_file": "C:\\Users\\praja\\OneDrive\\Desktop\\test-env\\repositories\\kairo-phantom\\phantom-core\\src\\cua\\cua_executor.rs", "source_location": "L370"}, {"caller_nid": "cua_cua_executor_find_cua_driver", "callee": "join", "is_member_call": true, "source_file": "C:\\Users\\praja\\OneDrive\\Desktop\\test-env\\repositories\\kairo-phantom\\phantom-core\\src\\cua\\cua_executor.rs", "source_location": "L371"}, {"caller_nid": "cua_cua_executor_find_cua_driver", "callee": "join", "is_member_call": true, "source_file": "C:\\Users\\praja\\OneDrive\\Desktop\\test-env\\repositories\\kairo-phantom\\phantom-core\\src\\cua\\cua_executor.rs", "source_location": "L371"}, {"caller_nid": "cua_cua_executor_find_cua_driver", "callee": "join", "is_member_call": true, "source_file": "C:\\Users\\praja\\OneDrive\\Desktop\\test-env\\repositories\\kairo-phantom\\phantom-core\\src\\cua\\cua_executor.rs", "source_location": "L371"}, {"caller_nid": "cua_cua_executor_find_cua_driver", "callee": "flatten", "is_member_call": true, "source_file": "C:\\Users\\praja\\OneDrive\\Desktop\\test-env\\repositories\\kairo-phantom\\phantom-core\\src\\cua\\cua_executor.rs", "source_location": "L376"}, {"caller_nid": "cua_cua_executor_find_cua_driver", "callee": "into_iter", "is_member_call": true, "source_file": "C:\\Users\\praja\\OneDrive\\Desktop\\test-env\\repositories\\kairo-phantom\\phantom-core\\src\\cua\\cua_executor.rs", "source_location": "L376"}, {"caller_nid": "cua_cua_executor_find_cua_driver", "callee": "exists", "is_member_call": true, "source_file": "C:\\Users\\praja\\OneDrive\\Desktop\\test-env\\repositories\\kairo-phantom\\phantom-core\\src\\cua\\cua_executor.rs", "source_location": "L377"}, {"caller_nid": "cua_cua_executor_find_cua_driver", "callee": "output", "is_member_call": true, "source_file": "C:\\Users\\praja\\OneDrive\\Desktop\\test-env\\repositories\\kairo-phantom\\phantom-core\\src\\cua\\cua_executor.rs", "source_location": "L383"}, {"caller_nid": "cua_cua_executor_find_cua_driver", "callee": "arg", "is_member_call": true, "source_file": "C:\\Users\\praja\\OneDrive\\Desktop\\test-env\\repositories\\kairo-phantom\\phantom-core\\src\\cua\\cua_executor.rs", "source_location": "L383"}, {"caller_nid": "cua_cua_executor_find_cua_driver", "callee": "success", "is_member_call": true, "source_file": "C:\\Users\\praja\\OneDrive\\Desktop\\test-env\\repositories\\kairo-phantom\\phantom-core\\src\\cua\\cua_executor.rs", "source_location": "L387"}, {"caller_nid": "cua_cua_executor_find_cua_driver", "callee": "trim", "is_member_call": true, "source_file": "C:\\Users\\praja\\OneDrive\\Desktop\\test-env\\repositories\\kairo-phantom\\phantom-core\\src\\cua\\cua_executor.rs", "source_location": "L389"}, {"caller_nid": "cua_cua_executor_find_cua_driver", "callee": "unwrap_or", "is_member_call": true, "source_file": "C:\\Users\\praja\\OneDrive\\Desktop\\test-env\\repositories\\kairo-phantom\\phantom-core\\src\\cua\\cua_executor.rs", "source_location": "L389"}, {"caller_nid": "cua_cua_executor_find_cua_driver", "callee": "lines", "is_member_call": true, "source_file": "C:\\Users\\praja\\OneDrive\\Desktop\\test-env\\repositories\\kairo-phantom\\phantom-core\\src\\cua\\cua_executor.rs", "source_location": "L389"}, {"caller_nid": "cua_cua_executor_verify_action", "callee": "unwrap_or_default", "is_member_call": true, "source_file": "C:\\Users\\praja\\OneDrive\\Desktop\\test-env\\repositories\\kairo-phantom\\phantom-core\\src\\cua\\cua_executor.rs", "source_location": "L407"}, {"caller_nid": "cua_cua_executor_verify_action", "callee": "unwrap_or_default", "is_member_call": true, "source_file": "C:\\Users\\praja\\OneDrive\\Desktop\\test-env\\repositories\\kairo-phantom\\phantom-core\\src\\cua\\cua_executor.rs", "source_location": "L409"}, {"caller_nid": "cua_cua_executor_verify_action", "callee": "and_then", "is_member_call": true, "source_file": "C:\\Users\\praja\\OneDrive\\Desktop\\test-env\\repositories\\kairo-phantom\\phantom-core\\src\\cua\\cua_executor.rs", "source_location": "L409"}, {"caller_nid": "cua_cua_executor_verify_action", "callee": "as_ref", "is_member_call": true, "source_file": "C:\\Users\\praja\\OneDrive\\Desktop\\test-env\\repositories\\kairo-phantom\\phantom-core\\src\\cua\\cua_executor.rs", "source_location": "L409"}, {"caller_nid": "cua_cua_executor_verify_action", "callee": "unwrap_or_default", "is_member_call": true, "source_file": "C:\\Users\\praja\\OneDrive\\Desktop\\test-env\\repositories\\kairo-phantom\\phantom-core\\src\\cua\\cua_executor.rs", "source_location": "L416"}, {"caller_nid": "cua_cua_executor_verify_action", "callee": "is_available", "is_member_call": true, "source_file": "C:\\Users\\praja\\OneDrive\\Desktop\\test-env\\repositories\\kairo-phantom\\phantom-core\\src\\cua\\cua_executor.rs", "source_location": "L423"}, {"caller_nid": "cua_cua_executor_verify_action", "callee": "verify_action", "is_member_call": true, "source_file": "C:\\Users\\praja\\OneDrive\\Desktop\\test-env\\repositories\\kairo-phantom\\phantom-core\\src\\cua\\cua_executor.rs", "source_location": "L446"}, {"caller_nid": "cua_cua_executor_capture_screenshot", "callee": "as_millis", "is_member_call": true, "source_file": "C:\\Users\\praja\\OneDrive\\Desktop\\test-env\\repositories\\kairo-phantom\\phantom-core\\src\\cua\\cua_executor.rs", "source_location": "L489"}, {"caller_nid": "cua_cua_executor_capture_screenshot", "callee": "unwrap_or_default", "is_member_call": true, "source_file": "C:\\Users\\praja\\OneDrive\\Desktop\\test-env\\repositories\\kairo-phantom\\phantom-core\\src\\cua\\cua_executor.rs", "source_location": "L489"}, {"caller_nid": "cua_cua_executor_capture_screenshot", "callee": "duration_since", "is_member_call": true, "source_file": "C:\\Users\\praja\\OneDrive\\Desktop\\test-env\\repositories\\kairo-phantom\\phantom-core\\src\\cua\\cua_executor.rs", "source_location": "L489"}, {"caller_nid": "cua_cua_executor_capture_screenshot", "callee": "join", "is_member_call": true, "source_file": "C:\\Users\\praja\\OneDrive\\Desktop\\test-env\\repositories\\kairo-phantom\\phantom-core\\src\\cua\\cua_executor.rs", "source_location": "L494"}, {"caller_nid": "cua_cua_executor_capture_screenshot", "callee": "join", "is_member_call": true, "source_file": "C:\\Users\\praja\\OneDrive\\Desktop\\test-env\\repositories\\kairo-phantom\\phantom-core\\src\\cua\\cua_executor.rs", "source_location": "L494"}, {"caller_nid": "cua_cua_executor_capture_screenshot", "callee": "join", "is_member_call": true, "source_file": "C:\\Users\\praja\\OneDrive\\Desktop\\test-env\\repositories\\kairo-phantom\\phantom-core\\src\\cua\\cua_executor.rs", "source_location": "L497"}, {"caller_nid": "cua_cua_executor_capture_screenshot", "callee": "output", "is_member_call": true, "source_file": "C:\\Users\\praja\\OneDrive\\Desktop\\test-env\\repositories\\kairo-phantom\\phantom-core\\src\\cua\\cua_executor.rs", "source_location": "L500"}, {"caller_nid": "cua_cua_executor_capture_screenshot", "callee": "args", "is_member_call": true, "source_file": "C:\\Users\\praja\\OneDrive\\Desktop\\test-env\\repositories\\kairo-phantom\\phantom-core\\src\\cua\\cua_executor.rs", "source_location": "L500"}, {"caller_nid": "cua_cua_executor_capture_screenshot", "callee": "unwrap_or", "is_member_call": true, "source_file": "C:\\Users\\praja\\OneDrive\\Desktop\\test-env\\repositories\\kairo-phantom\\phantom-core\\src\\cua\\cua_executor.rs", "source_location": "L501"}, {"caller_nid": "cua_cua_executor_capture_screenshot", "callee": "to_str", "is_member_call": true, "source_file": "C:\\Users\\praja\\OneDrive\\Desktop\\test-env\\repositories\\kairo-phantom\\phantom-core\\src\\cua\\cua_executor.rs", "source_location": "L501"}, {"caller_nid": "cua_cua_executor_capture_screenshot", "callee": "success", "is_member_call": true, "source_file": "C:\\Users\\praja\\OneDrive\\Desktop\\test-env\\repositories\\kairo-phantom\\phantom-core\\src\\cua\\cua_executor.rs", "source_location": "L505"}, {"caller_nid": "cua_cua_executor_capture_screenshot", "callee": "to_string_lossy", "is_member_call": true, "source_file": "C:\\Users\\praja\\OneDrive\\Desktop\\test-env\\repositories\\kairo-phantom\\phantom-core\\src\\cua\\cua_executor.rs", "source_location": "L505"}, {"caller_nid": "cua_cua_executor_capture_before_screenshot", "callee": "as_millis", "is_member_call": true, "source_file": "C:\\Users\\praja\\OneDrive\\Desktop\\test-env\\repositories\\kairo-phantom\\phantom-core\\src\\cua\\cua_executor.rs", "source_location": "L512"}, {"caller_nid": "cua_cua_executor_capture_before_screenshot", "callee": "unwrap_or_default", "is_member_call": true, "source_file": "C:\\Users\\praja\\OneDrive\\Desktop\\test-env\\repositories\\kairo-phantom\\phantom-core\\src\\cua\\cua_executor.rs", "source_location": "L512"}, {"caller_nid": "cua_cua_executor_capture_before_screenshot", "callee": "duration_since", "is_member_call": true, "source_file": "C:\\Users\\praja\\OneDrive\\Desktop\\test-env\\repositories\\kairo-phantom\\phantom-core\\src\\cua\\cua_executor.rs", "source_location": "L512"}, {"caller_nid": "cua_cua_executor_capture_before_screenshot", "callee": "join", "is_member_call": true, "source_file": "C:\\Users\\praja\\OneDrive\\Desktop\\test-env\\repositories\\kairo-phantom\\phantom-core\\src\\cua\\cua_executor.rs", "source_location": "L517"}, {"caller_nid": "cua_cua_executor_capture_before_screenshot", "callee": "join", "is_member_call": true, "source_file": "C:\\Users\\praja\\OneDrive\\Desktop\\test-env\\repositories\\kairo-phantom\\phantom-core\\src\\cua\\cua_executor.rs", "source_location": "L517"}, {"caller_nid": "cua_cua_executor_capture_before_screenshot", "callee": "join", "is_member_call": true, "source_file": "C:\\Users\\praja\\OneDrive\\Desktop\\test-env\\repositories\\kairo-phantom\\phantom-core\\src\\cua\\cua_executor.rs", "source_location": "L520"}, {"caller_nid": "cua_cua_executor_capture_before_screenshot", "callee": "output", "is_member_call": true, "source_file": "C:\\Users\\praja\\OneDrive\\Desktop\\test-env\\repositories\\kairo-phantom\\phantom-core\\src\\cua\\cua_executor.rs", "source_location": "L523"}, {"caller_nid": "cua_cua_executor_capture_before_screenshot", "callee": "args", "is_member_call": true, "source_file": "C:\\Users\\praja\\OneDrive\\Desktop\\test-env\\repositories\\kairo-phantom\\phantom-core\\src\\cua\\cua_executor.rs", "source_location": "L523"}, {"caller_nid": "cua_cua_executor_capture_before_screenshot", "callee": "unwrap_or", "is_member_call": true, "source_file": "C:\\Users\\praja\\OneDrive\\Desktop\\test-env\\repositories\\kairo-phantom\\phantom-core\\src\\cua\\cua_executor.rs", "source_location": "L524"}, {"caller_nid": "cua_cua_executor_capture_before_screenshot", "callee": "to_str", "is_member_call": true, "source_file": "C:\\Users\\praja\\OneDrive\\Desktop\\test-env\\repositories\\kairo-phantom\\phantom-core\\src\\cua\\cua_executor.rs", "source_location": "L524"}, {"caller_nid": "cua_cua_executor_capture_before_screenshot", "callee": "success", "is_member_call": true, "source_file": "C:\\Users\\praja\\OneDrive\\Desktop\\test-env\\repositories\\kairo-phantom\\phantom-core\\src\\cua\\cua_executor.rs", "source_location": "L528"}, {"caller_nid": "cua_cua_executor_capture_before_screenshot", "callee": "to_string_lossy", "is_member_call": true, "source_file": "C:\\Users\\praja\\OneDrive\\Desktop\\test-env\\repositories\\kairo-phantom\\phantom-core\\src\\cua\\cua_executor.rs", "source_location": "L528"}, {"caller_nid": "cua_cua_executor_audit_log", "callee": "join", "is_member_call": true, "source_file": "C:\\Users\\praja\\OneDrive\\Desktop\\test-env\\repositories\\kairo-phantom\\phantom-core\\src\\cua\\cua_executor.rs", "source_location": "L569"}, {"caller_nid": "cua_cua_executor_audit_log", "callee": "join", "is_member_call": true, "source_file": "C:\\Users\\praja\\OneDrive\\Desktop\\test-env\\repositories\\kairo-phantom\\phantom-core\\src\\cua\\cua_executor.rs", "source_location": "L574"}, {"caller_nid": "cua_cua_executor_audit_log", "callee": "format", "is_member_call": true, "source_file": "C:\\Users\\praja\\OneDrive\\Desktop\\test-env\\repositories\\kairo-phantom\\phantom-core\\src\\cua\\cua_executor.rs", "source_location": "L576"}, {"caller_nid": "cua_cua_executor_audit_log", "callee": "append", "is_member_call": true, "source_file": "C:\\Users\\praja\\OneDrive\\Desktop\\test-env\\repositories\\kairo-phantom\\phantom-core\\src\\cua\\cua_executor.rs", "source_location": "L592"}, {"caller_nid": "cua_cua_executor_audit_log", "callee": "create", "is_member_call": true, "source_file": "C:\\Users\\praja\\OneDrive\\Desktop\\test-env\\repositories\\kairo-phantom\\phantom-core\\src\\cua\\cua_executor.rs", "source_location": "L592"}, {"caller_nid": "cua_cua_executor_audit_log", "callee": "write_all", "is_member_call": true, "source_file": "C:\\Users\\praja\\OneDrive\\Desktop\\test-env\\repositories\\kairo-phantom\\phantom-core\\src\\cua\\cua_executor.rs", "source_location": "L597"}, {"caller_nid": "cua_cua_executor_audit_log", "callee": "as_bytes", "is_member_call": true, "source_file": "C:\\Users\\praja\\OneDrive\\Desktop\\test-env\\repositories\\kairo-phantom\\phantom-core\\src\\cua\\cua_executor.rs", "source_location": "L597"}]}