{"nodes": [{"id": "c_users_praja_onedrive_desktop_test_env_repositories_kairo_phantom_third_party_notices_md", "label": "THIRD_PARTY_NOTICES.md", "file_type": "document", "source_file": "C:\\Users\\praja\\OneDrive\\Desktop\\test-env\\repositories\\kairo-phantom\\THIRD_PARTY_NOTICES.md", "source_location": "L1"}, {"id": "kairo_phantom_third_party_notices_third_party_notices", "label": "Third-Party Notices", "file_type": "document", "source_file": "C:\\Users\\praja\\OneDrive\\Desktop\\test-env\\repositories\\kairo-phantom\\THIRD_PARTY_NOTICES.md", "source_location": "L1"}, {"id": "kairo_phantom_third_party_notices_core_runtime", "label": "Core Runtime", "file_type": "document", "source_file": "C:\\Users\\praja\\OneDrive\\Desktop\\test-env\\repositories\\kairo-phantom\\THIRD_PARTY_NOTICES.md", "source_location": "L9"}, {"id": "kairo_phantom_third_party_notices_ai_inference", "label": "AI & Inference", "file_type": "document", "source_file": "C:\\Users\\praja\\OneDrive\\Desktop\\test-env\\repositories\\kairo-phantom\\THIRD_PARTY_NOTICES.md", "source_location": "L20"}, {"id": "kairo_phantom_third_party_notices_os_integration_input", "label": "OS Integration & Input", "file_type": "document", "source_file": "C:\\Users\\praja\\OneDrive\\Desktop\\test-env\\repositories\\kairo-phantom\\THIRD_PARTY_NOTICES.md", "source_location": "L28"}, {"id": "kairo_phantom_third_party_notices_domain_8_multimodal_input", "label": "Domain 8: Multimodal Input", "file_type": "document", "source_file": "C:\\Users\\praja\\OneDrive\\Desktop\\test-env\\repositories\\kairo-phantom\\THIRD_PARTY_NOTICES.md", "source_location": "L38"}, {"id": "kairo_phantom_third_party_notices_memory_storage", "label": "Memory & Storage", "file_type": "document", "source_file": "C:\\Users\\praja\\OneDrive\\Desktop\\test-env\\repositories\\kairo-phantom\\THIRD_PARTY_NOTICES.md", "source_location": "L49"}, {"id": "kairo_phantom_third_party_notices_crdt_collaboration", "label": "CRDT & Collaboration", "file_type": "document", "source_file": "C:\\Users\\praja\\OneDrive\\Desktop\\test-env\\repositories\\kairo-phantom\\THIRD_PARTY_NOTICES.md", "source_location": "L58"}, {"id": "kairo_phantom_third_party_notices_wasm_sandbox", "label": "WASM Sandbox", "file_type": "document", "source_file": "C:\\Users\\praja\\OneDrive\\Desktop\\test-env\\repositories\\kairo-phantom\\THIRD_PARTY_NOTICES.md", "source_location": "L64"}, {"id": "kairo_phantom_third_party_notices_ui_overlay", "label": "UI & Overlay", "file_type": "document", "source_file": "C:\\Users\\praja\\OneDrive\\Desktop\\test-env\\repositories\\kairo-phantom\\THIRD_PARTY_NOTICES.md", "source_location": "L72"}, {"id": "kairo_phantom_third_party_notices_data_formats_parsing", "label": "Data Formats & Parsing", "file_type": "document", "source_file": "C:\\Users\\praja\\OneDrive\\Desktop\\test-env\\repositories\\kairo-phantom\\THIRD_PARTY_NOTICES.md", "source_location": "L79"}, {"id": "kairo_phantom_third_party_notices_cryptography_security", "label": "Cryptography & Security", "file_type": "document", "source_file": "C:\\Users\\praja\\OneDrive\\Desktop\\test-env\\repositories\\kairo-phantom\\THIRD_PARTY_NOTICES.md", "source_location": "L87"}, {"id": "kairo_phantom_third_party_notices_testing", "label": "Testing", "file_type": "document", "source_file": "C:\\Users\\praja\\OneDrive\\Desktop\\test-env\\repositories\\kairo-phantom\\THIRD_PARTY_NOTICES.md", "source_location": "L97"}, {"id": "kairo_phantom_third_party_notices_domain_9_enterprise_governance_compliance", "label": "Domain 9: Enterprise Governance & Compliance", "file_type": "document", "source_file": "C:\\Users\\praja\\OneDrive\\Desktop\\test-env\\repositories\\kairo-phantom\\THIRD_PARTY_NOTICES.md", "source_location": "L107"}, {"id": "kairo_phantom_third_party_notices_identity_authentication", "label": "Identity & Authentication", "file_type": "document", "source_file": "C:\\Users\\praja\\OneDrive\\Desktop\\test-env\\repositories\\kairo-phantom\\THIRD_PARTY_NOTICES.md", "source_location": "L109"}, {"id": "kairo_phantom_third_party_notices_agent_identity_spiffe", "label": "Agent Identity (SPIFFE)", "file_type": "document", "source_file": "C:\\Users\\praja\\OneDrive\\Desktop\\test-env\\repositories\\kairo-phantom\\THIRD_PARTY_NOTICES.md", "source_location": "L116"}, {"id": "kairo_phantom_third_party_notices_audit_logging_siem", "label": "Audit Logging & SIEM", "file_type": "document", "source_file": "C:\\Users\\praja\\OneDrive\\Desktop\\test-env\\repositories\\kairo-phantom\\THIRD_PARTY_NOTICES.md", "source_location": "L123"}, {"id": "kairo_phantom_third_party_notices_compliance_scanning", "label": "Compliance Scanning", "file_type": "document", "source_file": "C:\\Users\\praja\\OneDrive\\Desktop\\test-env\\repositories\\kairo-phantom\\THIRD_PARTY_NOTICES.md", "source_location": "L131"}, {"id": "kairo_phantom_third_party_notices_compliance_rule_sets_data", "label": "Compliance Rule Sets (Data)", "file_type": "document", "source_file": "C:\\Users\\praja\\OneDrive\\Desktop\\test-env\\repositories\\kairo-phantom\\THIRD_PARTY_NOTICES.md", "source_location": "L137"}, {"id": "kairo_phantom_third_party_notices_conceptual_inspirations", "label": "Conceptual Inspirations", "file_type": "document", "source_file": "C:\\Users\\praja\\OneDrive\\Desktop\\test-env\\repositories\\kairo-phantom\\THIRD_PARTY_NOTICES.md", "source_location": "L147"}, {"id": "kairo_phantom_third_party_notices_domain_8_voice_multimodal_input", "label": "Domain 8: Voice & Multimodal Input", "file_type": "document", "source_file": "C:\\Users\\praja\\OneDrive\\Desktop\\test-env\\repositories\\kairo-phantom\\THIRD_PARTY_NOTICES.md", "source_location": "L163"}, {"id": "kairo_phantom_third_party_notices_automatic_speech_recognition", "label": "Automatic Speech Recognition", "file_type": "document", "source_file": "C:\\Users\\praja\\OneDrive\\Desktop\\test-env\\repositories\\kairo-phantom\\THIRD_PARTY_NOTICES.md", "source_location": "L165"}, {"id": "kairo_phantom_third_party_notices_text_to_speech", "label": "Text-to-Speech", "file_type": "document", "source_file": "C:\\Users\\praja\\OneDrive\\Desktop\\test-env\\repositories\\kairo-phantom\\THIRD_PARTY_NOTICES.md", "source_location": "L172"}, {"id": "kairo_phantom_third_party_notices_wake_word_detection", "label": "Wake Word Detection", "file_type": "document", "source_file": "C:\\Users\\praja\\OneDrive\\Desktop\\test-env\\repositories\\kairo-phantom\\THIRD_PARTY_NOTICES.md", "source_location": "L180"}, {"id": "kairo_phantom_third_party_notices_audio_i_o", "label": "Audio I/O", "file_type": "document", "source_file": "C:\\Users\\praja\\OneDrive\\Desktop\\test-env\\repositories\\kairo-phantom\\THIRD_PARTY_NOTICES.md", "source_location": "L188"}, {"id": "kairo_phantom_third_party_notices_domain_11_cross_platform_hardening", "label": "Domain 11: Cross-Platform Hardening", "file_type": "document", "source_file": "C:\\Users\\praja\\OneDrive\\Desktop\\test-env\\repositories\\kairo-phantom\\THIRD_PARTY_NOTICES.md", "source_location": "L198"}, {"id": "kairo_phantom_third_party_notices_cross_platform_accessibility_layer", "label": "Cross-Platform Accessibility Layer", "file_type": "document", "source_file": "C:\\Users\\praja\\OneDrive\\Desktop\\test-env\\repositories\\kairo-phantom\\THIRD_PARTY_NOTICES.md", "source_location": "L200"}, {"id": "kairo_phantom_third_party_notices_linux_accessibility_tools_runtime_dependencies", "label": "Linux Accessibility Tools (Runtime Dependencies)", "file_type": "document", "source_file": "C:\\Users\\praja\\OneDrive\\Desktop\\test-env\\repositories\\kairo-phantom\\THIRD_PARTY_NOTICES.md", "source_location": "L209"}, {"id": "kairo_phantom_third_party_notices_macos_accessibility", "label": "macOS Accessibility", "file_type": "document", "source_file": "C:\\Users\\praja\\OneDrive\\Desktop\\test-env\\repositories\\kairo-phantom\\THIRD_PARTY_NOTICES.md", "source_location": "L224"}, {"id": "kairo_phantom_third_party_notices_cua_driver", "label": "cua-driver", "file_type": "document", "source_file": "C:\\Users\\praja\\OneDrive\\Desktop\\test-env\\repositories\\kairo-phantom\\THIRD_PARTY_NOTICES.md", "source_location": "L233"}], "edges": [{"source": "c_users_praja_onedrive_desktop_test_env_repositories_kairo_phantom_third_party_notices_md", "target": "kairo_phantom_third_party_notices_third_party_notices", "relation": "contains", "confidence": "EXTRACTED", "source_file": "C:\\Users\\praja\\OneDrive\\Desktop\\test-env\\repositories\\kairo-phantom\\THIRD_PARTY_NOTICES.md", "source_location": "L1", "weight": 1.0}, {"source": "kairo_phantom_third_party_notices_third_party_notices", "target": "kairo_phantom_third_party_notices_core_runtime", "relation": "contains", "confidence": "EXTRACTED", "source_file": "C:\\Users\\praja\\OneDrive\\Desktop\\test-env\\repositories\\kairo-phantom\\THIRD_PARTY_NOTICES.md", "source_location": "L9", "weight": 1.0}, {"source": "kairo_phantom_third_party_notices_third_party_notices", "target": "kairo_phantom_third_party_notices_ai_inference", "relation": "contains", "confidence": "EXTRACTED", "source_file": "C:\\Users\\praja\\OneDrive\\Desktop\\test-env\\repositories\\kairo-phantom\\THIRD_PARTY_NOTICES.md", "source_location": "L20", "weight": 1.0}, {"source": "kairo_phantom_third_party_notices_third_party_notices", "target": "kairo_phantom_third_party_notices_os_integration_input", "relation": "contains", "confidence": "EXTRACTED", "source_file": "C:\\Users\\praja\\OneDrive\\Desktop\\test-env\\repositories\\kairo-phantom\\THIRD_PARTY_NOTICES.md", "source_location": "L28", "weight": 1.0}, {"source": "kairo_phantom_third_party_notices_third_party_notices", "target": "kairo_phantom_third_party_notices_domain_8_multimodal_input", "relation": "contains", "confidence": "EXTRACTED", "source_file": "C:\\Users\\praja\\OneDrive\\Desktop\\test-env\\repositories\\kairo-phantom\\THIRD_PARTY_NOTICES.md", "source_location": "L38", "weight": 1.0}, {"source": "kairo_phantom_third_party_notices_third_party_notices", "target": "kairo_phantom_third_party_notices_memory_storage", "relation": "contains", "confidence": "EXTRACTED", "source_file": "C:\\Users\\praja\\OneDrive\\Desktop\\test-env\\repositories\\kairo-phantom\\THIRD_PARTY_NOTICES.md", "source_location": "L49", "weight": 1.0}, {"source": "kairo_phantom_third_party_notices_third_party_notices", "target": "kairo_phantom_third_party_notices_crdt_collaboration", "relation": "contains", "confidence": "EXTRACTED", "source_file": "C:\\Users\\praja\\OneDrive\\Desktop\\test-env\\repositories\\kairo-phantom\\THIRD_PARTY_NOTICES.md", "source_location": "L58", "weight": 1.0}, {"source": "kairo_phantom_third_party_notices_third_party_notices", "target": "kairo_phantom_third_party_notices_wasm_sandbox", "relation": "contains", "confidence": "EXTRACTED", "source_file": "C:\\Users\\praja\\OneDrive\\Desktop\\test-env\\repositories\\kairo-phantom\\THIRD_PARTY_NOTICES.md", "source_location": "L64", "weight": 1.0}, {"source": "kairo_phantom_third_party_notices_third_party_notices", "target": "kairo_phantom_third_party_notices_ui_overlay", "relation": "contains", "confidence": "EXTRACTED", "source_file": "C:\\Users\\praja\\OneDrive\\Desktop\\test-env\\repositories\\kairo-phantom\\THIRD_PARTY_NOTICES.md", "source_location": "L72", "weight": 1.0}, {"source": "kairo_phantom_third_party_notices_third_party_notices", "target": "kairo_phantom_third_party_notices_data_formats_parsing", "relation": "contains", "confidence": "EXTRACTED", "source_file": "C:\\Users\\praja\\OneDrive\\Desktop\\test-env\\repositories\\kairo-phantom\\THIRD_PARTY_NOTICES.md", "source_location": "L79", "weight": 1.0}, {"source": "kairo_phantom_third_party_notices_third_party_notices", "target": "kairo_phantom_third_party_notices_cryptography_security", "relation": "contains", "confidence": "EXTRACTED", "source_file": "C:\\Users\\praja\\OneDrive\\Desktop\\test-env\\repositories\\kairo-phantom\\THIRD_PARTY_NOTICES.md", "source_location": "L87", "weight": 1.0}, {"source": "kairo_phantom_third_party_notices_third_party_notices", "target": "kairo_phantom_third_party_notices_testing", "relation": "contains", "confidence": "EXTRACTED", "source_file": "C:\\Users\\praja\\OneDrive\\Desktop\\test-env\\repositories\\kairo-phantom\\THIRD_PARTY_NOTICES.md", "source_location": "L97", "weight": 1.0}, {"source": "kairo_phantom_third_party_notices_third_party_notices", "target": "kairo_phantom_third_party_notices_domain_9_enterprise_governance_compliance", "relation": "contains", "confidence": "EXTRACTED", "source_file": "C:\\Users\\praja\\OneDrive\\Desktop\\test-env\\repositories\\kairo-phantom\\THIRD_PARTY_NOTICES.md", "source_location": "L107", "weight": 1.0}, {"source": "kairo_phantom_third_party_notices_domain_9_enterprise_governance_compliance", "target": "kairo_phantom_third_party_notices_identity_authentication", "relation": "contains", "confidence": "EXTRACTED", "source_file": "C:\\Users\\praja\\OneDrive\\Desktop\\test-env\\repositories\\kairo-phantom\\THIRD_PARTY_NOTICES.md", "source_location": "L109", "weight": 1.0}, {"source": "kairo_phantom_third_party_notices_domain_9_enterprise_governance_compliance", "target": "kairo_phantom_third_party_notices_agent_identity_spiffe", "relation": "contains", "confidence": "EXTRACTED", "source_file": "C:\\Users\\praja\\OneDrive\\Desktop\\test-env\\repositories\\kairo-phantom\\THIRD_PARTY_NOTICES.md", "source_location": "L116", "weight": 1.0}, {"source": "kairo_phantom_third_party_notices_domain_9_enterprise_governance_compliance", "target": "kairo_phantom_third_party_notices_audit_logging_siem", "relation": "contains", "confidence": "EXTRACTED", "source_file": "C:\\Users\\praja\\OneDrive\\Desktop\\test-env\\repositories\\kairo-phantom\\THIRD_PARTY_NOTICES.md", "source_location": "L123", "weight": 1.0}, {"source": "kairo_phantom_third_party_notices_domain_9_enterprise_governance_compliance", "target": "kairo_phantom_third_party_notices_compliance_scanning", "relation": "contains", "confidence": "EXTRACTED", "source_file": "C:\\Users\\praja\\OneDrive\\Desktop\\test-env\\repositories\\kairo-phantom\\THIRD_PARTY_NOTICES.md", "source_location": "L131", "weight": 1.0}, {"source": "kairo_phantom_third_party_notices_domain_9_enterprise_governance_compliance", "target": "kairo_phantom_third_party_notices_compliance_rule_sets_data", "relation": "contains", "confidence": "EXTRACTED", "source_file": "C:\\Users\\praja\\OneDrive\\Desktop\\test-env\\repositories\\kairo-phantom\\THIRD_PARTY_NOTICES.md", "source_location": "L137", "weight": 1.0}, {"source": "kairo_phantom_third_party_notices_third_party_notices", "target": "kairo_phantom_third_party_notices_conceptual_inspirations", "relation": "contains", "confidence": "EXTRACTED", "source_file": "C:\\Users\\praja\\OneDrive\\Desktop\\test-env\\repositories\\kairo-phantom\\THIRD_PARTY_NOTICES.md", "source_location": "L147", "weight": 1.0}, {"source": "kairo_phantom_third_party_notices_third_party_notices", "target": "kairo_phantom_third_party_notices_domain_8_voice_multimodal_input", "relation": "contains", "confidence": "EXTRACTED", "source_file": "C:\\Users\\praja\\OneDrive\\Desktop\\test-env\\repositories\\kairo-phantom\\THIRD_PARTY_NOTICES.md", "source_location": "L163", "weight": 1.0}, {"source": "kairo_phantom_third_party_notices_domain_8_voice_multimodal_input", "target": "kairo_phantom_third_party_notices_automatic_speech_recognition", "relation": "contains", "confidence": "EXTRACTED", "source_file": "C:\\Users\\praja\\OneDrive\\Desktop\\test-env\\repositories\\kairo-phantom\\THIRD_PARTY_NOTICES.md", "source_location": "L165", "weight": 1.0}, {"source": "kairo_phantom_third_party_notices_domain_8_voice_multimodal_input", "target": "kairo_phantom_third_party_notices_text_to_speech", "relation": "contains", "confidence": "EXTRACTED", "source_file": "C:\\Users\\praja\\OneDrive\\Desktop\\test-env\\repositories\\kairo-phantom\\THIRD_PARTY_NOTICES.md", "source_location": "L172", "weight": 1.0}, {"source": "kairo_phantom_third_party_notices_domain_8_voice_multimodal_input", "target": "kairo_phantom_third_party_notices_wake_word_detection", "relation": "contains", "confidence": "EXTRACTED", "source_file": "C:\\Users\\praja\\OneDrive\\Desktop\\test-env\\repositories\\kairo-phantom\\THIRD_PARTY_NOTICES.md", "source_location": "L180", "weight": 1.0}, {"source": "kairo_phantom_third_party_notices_domain_8_voice_multimodal_input", "target": "kairo_phantom_third_party_notices_audio_i_o", "relation": "contains", "confidence": "EXTRACTED", "source_file": "C:\\Users\\praja\\OneDrive\\Desktop\\test-env\\repositories\\kairo-phantom\\THIRD_PARTY_NOTICES.md", "source_location": "L188", "weight": 1.0}, {"source": "kairo_phantom_third_party_notices_third_party_notices", "target": "kairo_phantom_third_party_notices_domain_11_cross_platform_hardening", "relation": "contains", "confidence": "EXTRACTED", "source_file": "C:\\Users\\praja\\OneDrive\\Desktop\\test-env\\repositories\\kairo-phantom\\THIRD_PARTY_NOTICES.md", "source_location": "L198", "weight": 1.0}, {"source": "kairo_phantom_third_party_notices_domain_11_cross_platform_hardening", "target": "kairo_phantom_third_party_notices_cross_platform_accessibility_layer", "relation": "contains", "confidence": "EXTRACTED", "source_file": "C:\\Users\\praja\\OneDrive\\Desktop\\test-env\\repositories\\kairo-phantom\\THIRD_PARTY_NOTICES.md", "source_location": "L200", "weight": 1.0}, {"source": "kairo_phantom_third_party_notices_domain_11_cross_platform_hardening", "target": "kairo_phantom_third_party_notices_linux_accessibility_tools_runtime_dependencies", "relation": "contains", "confidence": "EXTRACTED", "source_file": "C:\\Users\\praja\\OneDrive\\Desktop\\test-env\\repositories\\kairo-phantom\\THIRD_PARTY_NOTICES.md", "source_location": "L209", "weight": 1.0}, {"source": "kairo_phantom_third_party_notices_domain_11_cross_platform_hardening", "target": "kairo_phantom_third_party_notices_macos_accessibility", "relation": "contains", "confidence": "EXTRACTED", "source_file": "C:\\Users\\praja\\OneDrive\\Desktop\\test-env\\repositories\\kairo-phantom\\THIRD_PARTY_NOTICES.md", "source_location": "L224", "weight": 1.0}, {"source": "kairo_phantom_third_party_notices_third_party_notices", "target": "kairo_phantom_third_party_notices_cua_driver", "relation": "contains", "confidence": "EXTRACTED", "source_file": "C:\\Users\\praja\\OneDrive\\Desktop\\test-env\\repositories\\kairo-phantom\\THIRD_PARTY_NOTICES.md", "source_location": "L233", "weight": 1.0}], "input_tokens": 0, "output_tokens": 0}