{"nodes": [{"id": "c_users_praja_onedrive_desktop_test_env_repositories_kairo_phantom_scripts_mem_demo_py", "label": "mem_demo.py", "file_type": "code", "source_file": "C:\\Users\\praja\\OneDrive\\Desktop\\test-env\\repositories\\kairo-phantom\\scripts\\mem_demo.py", "source_location": "L1"}, {"id": "scripts_mem_demo_embed_text", "label": "embed_text()", "file_type": "code", "source_file": "C:\\Users\\praja\\OneDrive\\Desktop\\test-env\\repositories\\kairo-phantom\\scripts\\mem_demo.py", "source_location": "L16"}, {"id": "str", "label": "str", "file_type": "code", "source_file": "C:\\Users\\praja\\OneDrive\\Desktop\\test-env\\repositories\\kairo-phantom\\scripts\\mem_demo.py", "source_location": "L16"}, {"id": "float", "label": "float", "file_type": "code", "source_file": "C:\\Users\\praja\\OneDrive\\Desktop\\test-env\\repositories\\kairo-phantom\\scripts\\mem_demo.py", "source_location": "L16"}, {"id": "scripts_mem_demo_get_db_path", "label": "get_db_path()", "file_type": "code", "source_file": "C:\\Users\\praja\\OneDrive\\Desktop\\test-env\\repositories\\kairo-phantom\\scripts\\mem_demo.py", "source_location": "L25"}, {"id": "path", "label": "Path", "file_type": "code", "source_file": "C:\\Users\\praja\\OneDrive\\Desktop\\test-env\\repositories\\kairo-phantom\\scripts\\mem_demo.py", "source_location": "L25"}, {"id": "scripts_mem_demo_seed_session_1", "label": "seed_session_1()", "file_type": "code", "source_file": "C:\\Users\\praja\\OneDrive\\Desktop\\test-env\\repositories\\kairo-phantom\\scripts\\mem_demo.py", "source_location": "L31"}, {"id": "scripts_mem_demo_simulate_session_2", "label": "simulate_session_2()", "file_type": "code", "source_file": "C:\\Users\\praja\\OneDrive\\Desktop\\test-env\\repositories\\kairo-phantom\\scripts\\mem_demo.py", "source_location": "L101"}], "edges": [{"source": "c_users_praja_onedrive_desktop_test_env_repositories_kairo_phantom_scripts_mem_demo_py", "target": "os", "relation": "imports", "context": "import", "confidence": "EXTRACTED", "source_file": "C:\\Users\\praja\\OneDrive\\Desktop\\test-env\\repositories\\kairo-phantom\\scripts\\mem_demo.py", "source_location": "L1", "weight": 1.0}, {"source": "c_users_praja_onedrive_desktop_test_env_repositories_kairo_phantom_scripts_mem_demo_py", "target": "sqlite3", "relation": "imports", "context": "import", "confidence": "EXTRACTED", "source_file": "C:\\Users\\praja\\OneDrive\\Desktop\\test-env\\repositories\\kairo-phantom\\scripts\\mem_demo.py", "source_location": "L2", "weight": 1.0}, {"source": "c_users_praja_onedrive_desktop_test_env_repositories_kairo_phantom_scripts_mem_demo_py", "target": "sys", "relation": "imports", "context": "import", "confidence": "EXTRACTED", "source_file": "C:\\Users\\praja\\OneDrive\\Desktop\\test-env\\repositories\\kairo-phantom\\scripts\\mem_demo.py", "source_location": "L3", "weight": 1.0}, {"source": "c_users_praja_onedrive_desktop_test_env_repositories_kairo_phantom_scripts_mem_demo_py", "target": "uuid", "relation": "imports", "context": "import", "confidence": "EXTRACTED", "source_file": "C:\\Users\\praja\\OneDrive\\Desktop\\test-env\\repositories\\kairo-phantom\\scripts\\mem_demo.py", "source_location": "L4", "weight": 1.0}, {"source": "c_users_praja_onedrive_desktop_test_env_repositories_kairo_phantom_scripts_mem_demo_py", "target": "time", "relation": "imports", "context": "import", "confidence": "EXTRACTED", "source_file": "C:\\Users\\praja\\OneDrive\\Desktop\\test-env\\repositories\\kairo-phantom\\scripts\\mem_demo.py", "source_location": "L5", "weight": 1.0}, {"source": "c_users_praja_onedrive_desktop_test_env_repositories_kairo_phantom_scripts_mem_demo_py", "target": "pathlib", "relation": "imports_from", "context": "import", "confidence": "EXTRACTED", "source_file": "C:\\Users\\praja\\OneDrive\\Desktop\\test-env\\repositories\\kairo-phantom\\scripts\\mem_demo.py", "source_location": "L6", "weight": 1.0}, {"source": "c_users_praja_onedrive_desktop_test_env_repositories_kairo_phantom_scripts_mem_demo_py", "target": "kairo_sidecar_sidecar_embeddings", "relation": "imports_from", "context": "import", "confidence": "EXTRACTED", "source_file": "C:\\Users\\praja\\OneDrive\\Desktop\\test-env\\repositories\\kairo-phantom\\scripts\\mem_demo.py", "source_location": "L12", "weight": 1.0}, {"source": "c_users_praja_onedrive_desktop_test_env_repositories_kairo_phantom_scripts_mem_demo_py", "target": "hashlib", "relation": "imports", "context": "import", "confidence": "EXTRACTED", "source_file": "C:\\Users\\praja\\OneDrive\\Desktop\\test-env\\repositories\\kairo-phantom\\scripts\\mem_demo.py", "source_location": "L15", "weight": 1.0}, {"source": "c_users_praja_onedrive_desktop_test_env_repositories_kairo_phantom_scripts_mem_demo_py", "target": "scripts_mem_demo_embed_text", "relation": "contains", "confidence": "EXTRACTED", "source_file": "C:\\Users\\praja\\OneDrive\\Desktop\\test-env\\repositories\\kairo-phantom\\scripts\\mem_demo.py", "source_location": "L16", "weight": 1.0}, {"source": "scripts_mem_demo_embed_text", "target": "str", "relation": "references", "context": "parameter_type", "confidence": "EXTRACTED", "source_file": "C:\\Users\\praja\\OneDrive\\Desktop\\test-env\\repositories\\kairo-phantom\\scripts\\mem_demo.py", "source_location": "L16", "weight": 1.0}, {"source": "scripts_mem_demo_embed_text", "target": "float", "relation": "references", "context": "generic_arg", "confidence": "EXTRACTED", "source_file": "C:\\Users\\praja\\OneDrive\\Desktop\\test-env\\repositories\\kairo-phantom\\scripts\\mem_demo.py", "source_location": "L16", "weight": 1.0}, {"source": "c_users_praja_onedrive_desktop_test_env_repositories_kairo_phantom_scripts_mem_demo_py", "target": "scripts_mem_demo_get_db_path", "relation": "contains", "confidence": "EXTRACTED", "source_file": "C:\\Users\\praja\\OneDrive\\Desktop\\test-env\\repositories\\kairo-phantom\\scripts\\mem_demo.py", "source_location": "L25", "weight": 1.0}, {"source": "scripts_mem_demo_get_db_path", "target": "path", "relation": "references", "context": "return_type", "confidence": "EXTRACTED", "source_file": "C:\\Users\\praja\\OneDrive\\Desktop\\test-env\\repositories\\kairo-phantom\\scripts\\mem_demo.py", "source_location": "L25", "weight": 1.0}, {"source": "c_users_praja_onedrive_desktop_test_env_repositories_kairo_phantom_scripts_mem_demo_py", "target": "scripts_mem_demo_seed_session_1", "relation": "contains", "confidence": "EXTRACTED", "source_file": "C:\\Users\\praja\\OneDrive\\Desktop\\test-env\\repositories\\kairo-phantom\\scripts\\mem_demo.py", "source_location": "L31", "weight": 1.0}, {"source": "scripts_mem_demo_seed_session_1", "target": "path", "relation": "references", "context": "parameter_type", "confidence": "EXTRACTED", "source_file": "C:\\Users\\praja\\OneDrive\\Desktop\\test-env\\repositories\\kairo-phantom\\scripts\\mem_demo.py", "source_location": "L31", "weight": 1.0}, {"source": "c_users_praja_onedrive_desktop_test_env_repositories_kairo_phantom_scripts_mem_demo_py", "target": "scripts_mem_demo_simulate_session_2", "relation": "contains", "confidence": "EXTRACTED", "source_file": "C:\\Users\\praja\\OneDrive\\Desktop\\test-env\\repositories\\kairo-phantom\\scripts\\mem_demo.py", "source_location": "L101", "weight": 1.0}, {"source": "scripts_mem_demo_simulate_session_2", "target": "path", "relation": "references", "context": "parameter_type", "confidence": "EXTRACTED", "source_file": "C:\\Users\\praja\\OneDrive\\Desktop\\test-env\\repositories\\kairo-phantom\\scripts\\mem_demo.py", "source_location": "L101", "weight": 1.0}, {"source": "scripts_mem_demo_seed_session_1", "target": "scripts_mem_demo_embed_text", "relation": "calls", "context": "call", "confidence": "EXTRACTED", "source_file": "C:\\Users\\praja\\OneDrive\\Desktop\\test-env\\repositories\\kairo-phantom\\scripts\\mem_demo.py", "source_location": "L84", "weight": 1.0}], "raw_calls": [{"caller_nid": "scripts_mem_demo_embed_text", "callee": "digest", "is_member_call": true, "source_file": "C:\\Users\\praja\\OneDrive\\Desktop\\test-env\\repositories\\kairo-phantom\\scripts\\mem_demo.py", "source_location": "L19"}, {"caller_nid": "scripts_mem_demo_embed_text", "callee": "md5", "is_member_call": true, "source_file": "C:\\Users\\praja\\OneDrive\\Desktop\\test-env\\repositories\\kairo-phantom\\scripts\\mem_demo.py", "source_location": "L19"}, {"caller_nid": "scripts_mem_demo_embed_text", "callee": "encode", "is_member_call": true, "source_file": "C:\\Users\\praja\\OneDrive\\Desktop\\test-env\\repositories\\kairo-phantom\\scripts\\mem_demo.py", "source_location": "L19"}, {"caller_nid": "scripts_mem_demo_embed_text", "callee": "from_bytes", "is_member_call": true, "source_file": "C:\\Users\\praja\\OneDrive\\Desktop\\test-env\\repositories\\kairo-phantom\\scripts\\mem_demo.py", "source_location": "L20"}, {"caller_nid": "scripts_mem_demo_get_db_path", "callee": "home", "is_member_call": true, "source_file": "C:\\Users\\praja\\OneDrive\\Desktop\\test-env\\repositories\\kairo-phantom\\scripts\\mem_demo.py", "source_location": "L26"}, {"caller_nid": "scripts_mem_demo_get_db_path", "callee": "mkdir", "is_member_call": true, "source_file": "C:\\Users\\praja\\OneDrive\\Desktop\\test-env\\repositories\\kairo-phantom\\scripts\\mem_demo.py", "source_location": "L28"}, {"caller_nid": "scripts_mem_demo_seed_session_1", "callee": "connect", "is_member_call": true, "source_file": "C:\\Users\\praja\\OneDrive\\Desktop\\test-env\\repositories\\kairo-phantom\\scripts\\mem_demo.py", "source_location": "L33"}, {"caller_nid": "scripts_mem_demo_seed_session_1", "callee": "cursor", "is_member_call": true, "source_file": "C:\\Users\\praja\\OneDrive\\Desktop\\test-env\\repositories\\kairo-phantom\\scripts\\mem_demo.py", "source_location": "L34"}, {"caller_nid": "scripts_mem_demo_seed_session_1", "callee": "execute", "is_member_call": true, "source_file": "C:\\Users\\praja\\OneDrive\\Desktop\\test-env\\repositories\\kairo-phantom\\scripts\\mem_demo.py", "source_location": "L37"}, {"caller_nid": "scripts_mem_demo_seed_session_1", "callee": "execute", "is_member_call": true, "source_file": "C:\\Users\\praja\\OneDrive\\Desktop\\test-env\\repositories\\kairo-phantom\\scripts\\mem_demo.py", "source_location": "L77"}, {"caller_nid": "scripts_mem_demo_seed_session_1", "callee": "fetchone", "is_member_call": true, "source_file": "C:\\Users\\praja\\OneDrive\\Desktop\\test-env\\repositories\\kairo-phantom\\scripts\\mem_demo.py", "source_location": "L78"}, {"caller_nid": "scripts_mem_demo_seed_session_1", "callee": "uuid4", "is_member_call": true, "source_file": "C:\\Users\\praja\\OneDrive\\Desktop\\test-env\\repositories\\kairo-phantom\\scripts\\mem_demo.py", "source_location": "L82"}, {"caller_nid": "scripts_mem_demo_seed_session_1", "callee": "time", "is_member_call": true, "source_file": "C:\\Users\\praja\\OneDrive\\Desktop\\test-env\\repositories\\kairo-phantom\\scripts\\mem_demo.py", "source_location": "L83"}, {"caller_nid": "scripts_mem_demo_seed_session_1", "callee": "pack", "is_member_call": true, "source_file": "C:\\Users\\praja\\OneDrive\\Desktop\\test-env\\repositories\\kairo-phantom\\scripts\\mem_demo.py", "source_location": "L89"}, {"caller_nid": "scripts_mem_demo_seed_session_1", "callee": "execute", "is_member_call": true, "source_file": "C:\\Users\\praja\\OneDrive\\Desktop\\test-env\\repositories\\kairo-phantom\\scripts\\mem_demo.py", "source_location": "L91"}, {"caller_nid": "scripts_mem_demo_seed_session_1", "callee": "commit", "is_member_call": true, "source_file": "C:\\Users\\praja\\OneDrive\\Desktop\\test-env\\repositories\\kairo-phantom\\scripts\\mem_demo.py", "source_location": "L97"}, {"caller_nid": "scripts_mem_demo_seed_session_1", "callee": "close", "is_member_call": true, "source_file": "C:\\Users\\praja\\OneDrive\\Desktop\\test-env\\repositories\\kairo-phantom\\scripts\\mem_demo.py", "source_location": "L98"}, {"caller_nid": "scripts_mem_demo_simulate_session_2", "callee": "connect", "is_member_call": true, "source_file": "C:\\Users\\praja\\OneDrive\\Desktop\\test-env\\repositories\\kairo-phantom\\scripts\\mem_demo.py", "source_location": "L103"}, {"caller_nid": "scripts_mem_demo_simulate_session_2", "callee": "cursor", "is_member_call": true, "source_file": "C:\\Users\\praja\\OneDrive\\Desktop\\test-env\\repositories\\kairo-phantom\\scripts\\mem_demo.py", "source_location": "L104"}, {"caller_nid": "scripts_mem_demo_simulate_session_2", "callee": "execute", "is_member_call": true, "source_file": "C:\\Users\\praja\\OneDrive\\Desktop\\test-env\\repositories\\kairo-phantom\\scripts\\mem_demo.py", "source_location": "L107"}, {"caller_nid": "scripts_mem_demo_simulate_session_2", "callee": "fetchone", "is_member_call": true, "source_file": "C:\\Users\\praja\\OneDrive\\Desktop\\test-env\\repositories\\kairo-phantom\\scripts\\mem_demo.py", "source_location": "L114"}, {"caller_nid": "scripts_mem_demo_simulate_session_2", "callee": "execute", "is_member_call": true, "source_file": "C:\\Users\\praja\\OneDrive\\Desktop\\test-env\\repositories\\kairo-phantom\\scripts\\mem_demo.py", "source_location": "L124"}, {"caller_nid": "scripts_mem_demo_simulate_session_2", "callee": "fetchone", "is_member_call": true, "source_file": "C:\\Users\\praja\\OneDrive\\Desktop\\test-env\\repositories\\kairo-phantom\\scripts\\mem_demo.py", "source_location": "L131"}, {"caller_nid": "scripts_mem_demo_simulate_session_2", "callee": "close", "is_member_call": true, "source_file": "C:\\Users\\praja\\OneDrive\\Desktop\\test-env\\repositories\\kairo-phantom\\scripts\\mem_demo.py", "source_location": "L140"}]}